Workbook
Name rdrCancels: ChartData!$C$2:INDEX(ChartData!$C:$C,COUNTA(Monthly!$A:$A))
Name rdrCountryOptions: Lists!$A$1:INDEX(Lists!$A:$A,COUNTA(Country!$A:$A))
Name rdrMonthOptions: Lists!$B$1:INDEX(Lists!$B:$B,COUNTA(Monthly!$A:$A)-1)
Name rdrMonths: ChartData!$A$2:INDEX(ChartData!$A:$A,COUNTA(Monthly!$A:$A))
Name rdrSales: ChartData!$B$2:INDEX(ChartData!$B:$B,COUNTA(Monthly!$A:$A))

Sheet Dashboard
B1: RETAIL DATA RESCUE
B2: Merchandise reporting | GBP | independent portfolio by Hakan
B4: Country | F4: Start month | J4: End month
B5: All | F5: 2010-12 | J5: 2011-12
B6: Filters affect cards and monthly trend. Country/product rankings show full source.
B8: REPORTABLE SALES (GBP) | F8: MERCHANDISE CANCELLATIONS | J8: MERCHANDISE BALANCE (GBP)
B9: =SUMIFS(DashboardData!$D:$D,DashboardData!$A:$A,IF($B$5="All","*",$B$5),DashboardData!$C:$C,">="&DATE(VALUE(LEFT($F$5,4)),VALUE(RIGHT($F$5,2)),1),DashboardData!$C:$C,"<="&DATE(VALUE(LEFT($J$5,4)),VALUE(RIGHT($J$5,2)),1)) -> 10271433 | F9: =SUMIFS(DashboardData!$E:$E,DashboardData!$A:$A,IF($B$5="All","*",$B$5),DashboardData!$C:$C,">="&DATE(VALUE(LEFT($F$5,4)),VALUE(RIGHT($F$5,2)),1),DashboardData!$C:$C,"<="&DATE(VALUE(LEFT($J$5,4)),VALUE(RIGHT($J$5,2)),1)) -> 478724.18 | J9: =SUMIFS(DashboardData!$D:$D,DashboardData!$A:$A,IF($B$5="All","*",$B$5),DashboardData!$C:$C,">="&DATE(VALUE(LEFT($F$5,4)),VALUE(RIGHT($F$5,2)),1),DashboardData!$C:$C,"<="&DATE(VALUE(LEFT($J$5,4)),VALUE(RIGHT($J$5,2)),1))-SUMIFS(DashboardData!$E:$E,DashboardData!$A:$A,IF($B$5="All","*",$B$5),DashboardData!$C:$C,">="&DATE(VALUE(LEFT($F$5,4)),VALUE(RIGHT($F$5,2)),1),DashboardData!$C:$C,"<="&DATE(VALUE(LEFT($J$5,4)),VALUE(RIGHT($J$5,2)),1)) -> 9792708.9
B12: ELIGIBLE SALES INVOICES | F12: KNOWN CUSTOMER ROW COVERAGE | J12: ROWS WITH REVIEW FLAGS
B13: =SUMIFS(DashboardData!$H:$H,DashboardData!$A:$A,IF($B$5="All","*",$B$5),DashboardData!$C:$C,">="&DATE(VALUE(LEFT($F$5,4)),VALUE(RIGHT($F$5,2)),1),DashboardData!$C:$C,"<="&DATE(VALUE(LEFT($J$5,4)),VALUE(RIGHT($J$5,2)),1)) -> 19773 | F13: =IFERROR(SUMIFS(DashboardData!$G:$G,DashboardData!$A:$A,IF($B$5="All","*",$B$5),DashboardData!$C:$C,">="&DATE(VALUE(LEFT($F$5,4)),VALUE(RIGHT($F$5,2)),1),DashboardData!$C:$C,"<="&DATE(VALUE(LEFT($J$5,4)),VALUE(RIGHT($J$5,2)),1))/SUMIFS(DashboardData!$F:$F,DashboardData!$A:$A,IF($B$5="All","*",$B$5),DashboardData!$C:$C,">="&DATE(VALUE(LEFT($F$5,4)),VALUE(RIGHT($F$5,2)),1),DashboardData!$C:$C,"<="&DATE(VALUE(LEFT($J$5,4)),VALUE(RIGHT($J$5,2)),1)),0) -> 0.75098387 | J13: =SUMIFS(DashboardData!$I:$I,DashboardData!$A:$A,IF($B$5="All","*",$B$5),DashboardData!$C:$C,">="&DATE(VALUE(LEFT($F$5,4)),VALUE(RIGHT($F$5,2)),1),DashboardData!$C:$C,"<="&DATE(VALUE(LEFT($J$5,4)),VALUE(RIGHT($J$5,2)),1)) -> 232181
B16: =RefreshInfo!B2&" | Reference built UTC: "&RefreshInfo!A2 -> Reference dashboard | Embedded audit queries refreshed in Excel 2021; full-model integration pending | Reference built UTC: 2026-10-12T08:33:17.842813+00:00
B18: Observed edge windows: Dec 2010 = 01–23 Dec; Dec 2011 = 01–09 Dec. No full-year growth claim.
B54: Scope: positive-priced merchandise sales; eligible merchandise cancellations shown separately. Special operations excluded. Exact duplicates retained.
B56: Review flags overlap reporting scope. Merchandise balance is not accounting revenue. Cancellation does not establish a physical return.

Sheet qMissingValues
A1: Field | B1: MissingRows
A2: InvoiceNo | B2: 0
A3: StockCode | B3: 0
A4: Description | B4: 1454
A5: Quantity | B5: 0
A6: InvoiceDate | B6: 0
A7: UnitPrice | B7: 0
A8: CustomerID | B8: 135080
A9: Country | B9: 0

Sheet SourceCheck
A1: Kontrol | B1: Sonuç
A2: Veri satırı sayısı | B2: 541909
A3: Sütun sayısı | B3: 8

Sheet Settings
A1: Source parameter — change to your local full file path
A5: SourcePath | B5: ValidateBaseline
A6: C:\RetailDataRescue\raw\Online Retail.xlsx | B6: TRUE
A9: Baseline TRUE = published UCI source; FALSE = labelled append test/new source.
A11: Four audit queries are embedded. Full reporting M sources are in power_query/; see the setup guide.
A14: See docs/KURULUM_YENILEME_TR.md for precise installation and table destinations.
A17: Four-decimal fixed-scale arithmetic; reconciliation tolerance GBP 0.0001.

Sheet KPI
A1: Metric | B1: Value
A2: SourceRows | B2: 541909
A3: RawInvoiceIDs | B3: 25900
A4: RawSignedAmountGBP | B4: 9747747.9
A5: ReportableSalesGBP | B5: 10271433
A6: MerchandiseCancellationGBP | B6: 478724.18
A7: MerchandiseBalanceGBP | B7: 9792708.9
A8: EligibleSalesInvoiceIDs | B8: 19773
A9: SalesRows | B9: 527761
A10: KnownCustomerSalesRows | B10: 396340
A11: KnownCustomerRowCoverage | B11: 0.75098387
A12: KnownCustomerAmountCoverage | B12: 0.85295466
A13: KnownCustomerIDs | B13: 4334
... A17: DuplicateExtraSignedAmountGBP | B17: 21740.98

Sheet Monthly
A1: Month | B1: SourceRows | C1: SalesRows | D1: SalesInvoiceIDs | E1: SalesGBP | F1: CancellationGBP | G1: BalanceGBP | H1: ReviewRows | I1: FirstObservedDate | J1: LastObservedDate | K1: PeriodNote
A2: 2010-12 | B2: 42481 | C2: 41315 | D2: 1550 | E2: 777931.77 | F2: 17607.86 | G2: 760323.91 | H2: 22229 | I2: 2010-12-01 | J2: 2010-12-23 | K2: Edge month: observed transaction window only
A3: 2011-01 | B3: 35147 | C3: 34148 | D3: 1081 | E3: 671933.19 | F3: 91526.3 | G3: 580406.89 | H3: 17860 | I3: 2011-01-04 | J3: 2011-01-31 | K3: Observed month; no completeness certification
A4: 2011-02 | B4: 27707 | C4: 26964 | D4: 1093 | E4: 508886.2 | F4: 8375.87 | G4: 500510.33 | H4: 11654 | I4: 2011-02-01 | J4: 2011-02-28 | K4: Observed month; no completeness certification
A5: 2011-03 | B5: 36748 | C5: 35607 | D5: 1440 | E5: 691257.61 | F5: 10675.3 | G5: 680582.31 | H5: 14874 | I5: 2011-03-01 | J5: 2011-03-31 | K5: Observed month; no completeness certification
A6: 2011-04 | B6: 29916 | C6: 28957 | D6: 1235 | E6: 516218.12 | F6: 33316.91 | G6: 482901.21 | H6: 11812 | I6: 2011-04-01 | J6: 2011-04-28 | K6: Observed month; no completeness certification
A7: 2011-05 | B7: 37030 | C7: 35979 | D7: 1668 | E7: 741192.41 | F7: 8948.23 | G7: 732244.18 | H7: 15321 | I7: 2011-05-01 | J7: 2011-05-31 | K7: Observed month; no completeness certification
A8: 2011-06 | B8: 36874 | C8: 35773 | D8: 1525 | E8: 738751.87 | F8: 13760.84 | G8: 724991.03 | H8: 15966 | I8: 2011-06-01 | J8: 2011-06-30 | K8: Observed month; no completeness certification
A9: 2011-07 | B9: 39518 | C9: 38444 | D9: 1452 | E9: 689364.41 | F9: 11409.21 | G9: 677955.2 | H9: 18721 | I9: 2011-07-01 | J9: 2011-07-31 | K9: Observed month; no completeness certification
A10: 2011-08 | B10: 35284 | C10: 34326 | D10: 1339 | E10: 725513.5 | F10: 22929.52 | G10: 702583.98 | H10: 14162 | I10: 2011-08-01 | J10: 2011-08-31 | K10: Observed month; no completeness certification
A11: 2011-09 | B11: 50226 | C11: 49057 | D11: 1818 | E11: 1030475.4 | F11: 17044.68 | G11: 1013430.7 | H11: 19450 | I11: 2011-09-01 | J11: 2011-09-30 | K11: Observed month; no completeness certification
A12: 2011-10 | B12: 60742 | C12: 59068 | D12: 2005 | E12: 1106669.8 | F12: 43992.16 | G12: 1062677.7 | H12: 23302 | I12: 2011-10-02 | J12: 2011-10-31 | K12: Observed month; no completeness certification
A13: 2011-11 | B13: 84711 | C13: 83092 | D13: 2751 | E13: 1457745.5 | F13: 25010.54 | G13: 1432735 | H13: 35290 | I13: 2011-11-01 | J13: 2011-11-30 | K13: Observed month; no completeness certification
A14: 2011-12 | B14: 25525 | C14: 25031 | D14: 816 | E14: 615493.27 | F14: 174126.76 | G14: 441366.51 | H14: 11540 | I14: 2011-12-01 | J14: 2011-12-09 | K14: Edge month: observed transaction window only

Sheet Country
A1: Country | B1: SalesGBP | C1: CancellationGBP | D1: BalanceGBP | E1: SalesRows | F1: SalesInvoiceIDs
A2: United Kingdom | B2: 8747561.7 | C2: 445843.38 | D2: 8301718.3 | E2: 484007 | F2: 17901
A3: Netherlands | B3: 283889.34 | C3: 409.8 | D3: 283479.54 | E3: 2322 | F3: 93
A4: EIRE | B4: 271164.3 | C4: 11500.84 | D4: 259663.46 | E4: 7779 | F4: 282
A5: Germany | B5: 205569.89 | C5: 4761.49 | D5: 200808.4 | E5: 8658 | F5: 443
A6: France | B6: 184582.74 | C6: 2419.35 | D6: 182163.39 | E6: 8100 | F6: 382
A7: Australia | B7: 138171.31 | C7: 1181.31 | D7: 136990 | E7: 1181 | F7: 56
A8: Spain | B8: 55725.11 | C8: 3959.91 | D8: 51765.2 | E8: 2422 | F8: 88
A9: Switzerland | B9: 53087.9 | C9: 582.55 | D9: 52505.35 | E9: 1935 | F9: 50
A10: Japan | B10: 37416.37 | C10: 1996.58 | D10: 35419.79 | E10: 321 | F10: 19
A11: Belgium | B11: 36927.34 | C11: 264.38 | D11: 36662.96 | E11: 1935 | F11: 98
A12: Sweden | B12: 36839.33 | C12: 1662.42 | D12: 35176.91 | E12: 428 | F12: 34
A13: Norway | B13: 32454.64 | C13: 161.68 | D13: 32292.96 | E13: 1048 | F13: 32
... A39: Saudi Arabia | B39: 145.92 | C39: 14.75 | D39: 131.17 | E39: 9 | F39: 1

Sheet Product
A1: StockCode | B1: SalesGBP | C1: CancellationGBP | D1: BalanceGBP | E1: SalesRows | F1: SalesInvoiceIDs
A2: 22423 | B2: 174484.74 | C2: 9722.55 | D2: 164762.19 | E2: 2017 | F2: 1988
A3: 23843 | B3: 168469.6 | C3: 168469.6 | D3: 0 | E3: 1 | F3: 1
A4: 85123A | B4: 104518.8 | C4: 6624.3 | D4: 97894.5 | E4: 2265 | F4: 2198
A5: 47566 | B5: 99504.33 | C5: 1201.35 | D5: 98302.98 | E5: 1706 | F5: 1685
A6: 85099B | B6: 94340.05 | C6: 1984.02 | D6: 92356.03 | E6: 2112 | F6: 2089
A7: 23166 | B7: 81700.92 | C7: 77479.64 | D7: 4221.28 | E7: 250 | F7: 247
A8: 23084 | B8: 66964.99 | C8: 208.4 | D8: 66756.59 | E8: 1036 | F8: 994
A9: 22086 | B9: 64952.29 | C9: 1160.35 | D9: 63791.94 | E9: 1200 | F9: 1160
A10: 84879 | B10: 59094.93 | C10: 135.2 | D10: 58959.73 | E10: 1489 | F10: 1455
A11: 79321 | B11: 54117.76 | C11: 349.7 | D11: 53768.06 | E11: 670 | F11: 661
A12: 22502 | B12: 51426.62 | C12: 385.25 | D12: 51041.37 | E12: 469 | F12: 463
A13: 22197 | B13: 51354.02 | C13: 366.55 | D13: 50987.47 | E13: 1426 | F13: 1392
... A3923: 85098B | B3923: 0 | C3923: 3.75 | D3923: -3.75 | E3923: 0 | F3923: 0

Sheet Reconciliation
A1: TransactionClass | B1: Rows | C1: InvoiceIDs | D1: AmountUnits4 | E1: SignedAmountGBP | F1: ReviewFlagRows
A2: MerchandiseSale | B2: 527761 | C2: 19773 | D2: 102714330630 | E2: 10271433 | F2: 226068
A3: MerchandiseCancellation | B3: 8704 | C3: 3422 | D3: -4787241800 | E3: -478724.18 | F3: 2572
A4: SpecialOperation | B4: 2946 | C4: 2769 | D4: -449609490 | E4: -44960.949 | F4: 1043
A5: ZeroPriceAdjustment | B5: 1335 | C5: 1335 | D5: 0 | E5: 0 | F5: 1335
A6: UnresolvedReview | B6: 1163 | C6: 805 | D6: 0 | E6: 0 | F6: 1163

Sheet Bridge
A1: Step | B1: ChangeGBP | C1: BalanceGBP
A2: Raw signed transactions | B2: 9747747.9 | C2: 9747747.9
A3: Separate SpecialOperation | B3: 44960.949 | C3: 9792708.9
A4: Separate ZeroPriceAdjustment | B4: 0 | C4: 9792708.9
A5: Separate UnresolvedReview | B5: 0 | C5: 9792708.9
A6: Merchandise signed balance | B6: 0 | C6: 9792708.9

Sheet Quality
A1: Flag | B1: Label | C1: Kind | D1: Rows | E1: SourceRowExample | F1: Definition
A2: HasMissingCustomer | B2: Missing customer ID | C2: review | D2: 135080 | E2: 624.0 | F2: Customer ID null; sale remains eligible
A3: HasMissingDescription | B3: Missing description | C3: review | D3: 1454 | E3: 624.0 | F3: Description null or whitespace-only text
A4: HasNonTextDescription | B4: Non-text description | C4: review | D4: 1 | E4: 420393.0 | F4: Nonempty description is not text
A5: HasOuterWhitespace | B5: Description outer whitespace | C5: format | D5: 113452 | E5: 12.0 | F5: Raw text differs from trimmed text
A6: IsExactDuplicateMember | B6: Exact duplicate group member | C6: review | D6: 10147 | E6: 487.0 | F6: All eight raw fields equal; all group members
A7: IsDuplicateBeyondFirst | B7: Exact duplicate beyond first | C7: scenario | D7: 5268 | E7: 519.0 | F7: SourceRow greater than group minimum
A8: IsDescriptionVariantDuplicate | B8: Description-only duplicate candidate | C8: review | D8: 4 | E8: 199126.0 | F8: Seven other raw fields equal; descriptions differ
A9: HasMultipleDescriptions | B9: Code with multiple descriptions | C9: review | D9: 113465 | E9: 2.0 | F9: Code has >1 nonblank raw text description
A10: IsNonCNegative | B10: Negative quantity without C | C10: review | D10: 1336 | E10: 2408.0 | F10: Quantity < 0 and no C invoice prefix
A11: IsZeroPrice | B11: Zero price | C11: review | D11: 2515 | E11: 624.0 | F11: UnitPrice == 0
A12: IsNegativePrice | B12: Negative price | C12: review | D12: 2 | E12: 299985.0 | F12: UnitPrice < 0
A13: IsLargeAmount | B13: Large absolute line amount | C13: review | D13: 17 | E13: 15018.0 | F13: abs(LineAmount) >= GBP 10000
A14: IsUnmappedCode | B14: Unmapped nonstandard code | C14: review | D14: 0 | F14: Neither explicit code rule nor common merchandise format
A15: IsInvoicePatternException | B15: Invoice pattern outside numeric/C | C15: context | D15: 3 | E15: 299984.0 | F15: Neither six digits nor C + six digits
A16: IsCancellationCode | B16: C cancellation prefix | C16: context | D16: 9288 | E16: 143.0 | F16: InvoiceNo starts with uppercase C

Sheet Controls
A1: Control | B1: Expected | C1: Actual | D1: Status | E1: Scope
A2: Unique source RecordID | B2: 541909 | C2: 541909 | D2: PASS | E2: Python reference
A3: Source rows preserved | B3: 541909 | C3: 541909 | D3: PASS | E3: Python reference
A4: Exactly one class per row | B4: 541909 | C4: 541909 | D4: PASS | E4: Python reference
A5: No unassigned class | B5: 0 | C5: 0 | D5: PASS | E5: Python reference
A6: Class amounts reconcile (integer units) | B6: 97477479340 | C6: 97477479340 | D6: PASS | E6: Python reference
A7: Product dictionary join rows preserved | B7: 541909 | C7: 541909 | D7: PASS | E7: Python reference
A8: Product dictionary nonmissing matches | B8: 0 | C8: 0 | D8: PASS | E8: Python reference
A9: Monthly source rows reconcile | B9: 541909 | C9: 541909 | D9: PASS | E9: Python reference
A10: Monthly sales reconcile | B10: 10271433.063 | C10: 10271433.063 | D10: PASS | E10: Python reference
A11: Country sales reconcile | B11: 10271433.063 | C11: 10271433.063000001 | D11: PASS | E11: Python reference
A12: Product sales reconcile | B12: 10271433.063 | C12: 10271433.063 | D12: PASS | E12: Python reference
... A31: Real Excel / Power Query execution and refresh | B31: User runs Excel checklist | C31: Desktop Excel unavailable in Linux environment | D31: PENDING | E31: Excel required
A32: Sales invoice cube partition | B32: 19773 | C32: 19773 | D32: PASS | E32: Python reference

Sheet DuplicateScenario
A1: Scenario | B1: SourceRows | C1: RawAmountUnits4 | D1: RawSignedGBP | E1: SalesGBP | F1: CancellationGBP | G1: BalanceGBP | H1: SalesInvoiceIDs | I1: CustomerSalesIDs | J1: ReviewRows
A2: Main: retain all rows | B2: 541909 | C2: 97477479340 | D2: 9747747.9 | E2: 10271433 | F2: 478724.18 | G2: 9792708.9 | H2: 19773 | I2: 4334 | J2: 232181
A3: Alternative: first exact record only | B3: 536641 | C3: 97260069540 | D3: 9726007 | E3: 10247219 | F3: 475901.16 | G3: 9771318.2 | H3: 19773 | I3: 4334 | J3: 226913

Sheet BeforeAfter
A1: RecordID | B1: SourceRow | C1: InvoiceNo_Raw | D1: StockCode_Raw | E1: Description_Raw | F1: DescriptionTrim | G1: CustomerID_Raw | H1: CustomerID | I1: TransactionClass | J1: ReviewReasons | K1: LineAmount
A2: Online Retail.xlsx|Online Retail|000000012 | B2: 12 | C2: 536367 | D2: 22745 | E2: POPPY'S PLAYHOUSE BEDROOM | F2: POPPY'S PLAYHOUSE BEDROOM | G2: 13047 | H2: 13047 | I2: MerchandiseSale | K2: 12.6
A3: Online Retail.xlsx|Online Retail|000000487 | B3: 487 | C3: 536409 | D3: 22111 | E3: SCOTTIE DOG HOT WATER BOTTLE | F3: SCOTTIE DOG HOT WATER BOTTLE | G3: 17908 | H3: 17908 | I3: MerchandiseSale | J3: Exact duplicate group member | K3: 4.95
A4: Online Retail.xlsx|Online Retail|000000541 | B4: 541 | C4: 536409 | D4: 22111 | E4: SCOTTIE DOG HOT WATER BOTTLE | F4: SCOTTIE DOG HOT WATER BOTTLE | G4: 17908 | H4: 17908 | I4: MerchandiseSale | J4: Exact duplicate group member | K4: 4.95
A5: Online Retail.xlsx|Online Retail|000000624 | B5: 624 | C5: 536414 | D5: 22139 | I5: UnresolvedReview | J5: Missing customer ID; Missing description; Code with multiple descriptions; Zero price; Unresolved transaction class | K5: 0
A6: Online Retail.xlsx|Online Retail|000001445 | B6: 1445 | C6: 536544 | D6: 21773 | E6: DECORATIVE ROSE BATHROOM BOTTLE | F6: DECORATIVE ROSE BATHROOM BOTTLE | I6: MerchandiseSale | J6: Missing customer ID | K6: 2.51
A7: Online Retail.xlsx|Online Retail|000009304 | B7: 9304 | C7: 537197 | D7: 22841 | E7: ROUND CAKE TIN VINTAGE GREEN | F7: ROUND CAKE TIN VINTAGE GREEN | G7: 12647 | H7: 12647 | I7: UnresolvedReview | J7: Zero price; Unresolved transaction class | K7: 0
A8: Online Retail.xlsx|Online Retail|000199126 | B8: 199126 | C8: 554084 | D8: 23298 | E8: BUNTING , SPOTTY | F8: BUNTING , SPOTTY | G8: 12909 | H8: 12909 | I8: MerchandiseSale | J8: Description-only duplicate candidate; Code with multiple descriptions | K8: 14.85
A9: Online Retail.xlsx|Online Retail|000199146 | B9: 199146 | C9: 554084 | D9: 23298 | E9: SPOTTY BUNTING | F9: SPOTTY BUNTING | G9: 12909 | H9: 12909 | I9: MerchandiseSale | J9: Description-only duplicate candidate; Code with multiple descriptions | K9: 14.85
A10: Online Retail.xlsx|Online Retail|000299985 | B10: 299985 | C10: A563186 | D10: B | E10: Adjust bad debt | F10: Adjust bad debt | I10: SpecialOperation | J10: Missing customer ID; Negative price; Large absolute line amount | K10: -11062.06
A11: Online Retail.xlsx|Online Retail|000420393 | B11: 420393 | C11: 572891 | D11: 23343 | E11: 20713 | I11: UnresolvedReview | J11: Missing customer ID; Non-text description; Code with multiple descriptions; Negative quantity without C; Zero price; Unresolved transaction class | K11: 0
A12: Online Retail.xlsx|Online Retail|000540423 | B12: 540423 | C12: 581483 | D12: 23843 | E12: PAPER CRAFT , LITTLE BIRDIE | F12: PAPER CRAFT , LITTLE BIRDIE | G12: 16446 | H12: 16446 | I12: MerchandiseSale | J12: Large absolute line amount | K12: 168469.6
A13: Online Retail.xlsx|Online Retail|000540424 | B13: 540424 | C13: C581484 | D13: 23843 | E13: PAPER CRAFT , LITTLE BIRDIE | F13: PAPER CRAFT , LITTLE BIRDIE | G13: 16446 | H13: 16446 | I13: MerchandiseCancellation | J13: Large absolute line amount | K13: -168469.6

Sheet ProductDictionary
A1: StockCode | B1: DescriptionVariantCount | C1: TrimmedVariantCount | D1: NormalizedVariantCount | E1: RawDescriptions | F1: TrimmedDescriptions | G1: SafeDisplayLabel | H1: SourceRows
A2: 10002 | B2: 1 | C2: 1 | D2: 1 | E2: INFLATABLE POLITICAL GLOBE | F2: INFLATABLE POLITICAL GLOBE | G2: INFLATABLE POLITICAL GLOBE | H2: 73
A3: 10080 | B3: 2 | C3: 2 | D3: 2 | E3: GROOVY CACTUS INFLATABLE | check | F3: GROOVY CACTUS INFLATABLE | check | G3: [multiple/absent descriptions; use code] | H3: 24
A4: 10120 | B4: 1 | C4: 1 | D4: 1 | E4: DOGGY RUBBER | F4: DOGGY RUBBER | G4: DOGGY RUBBER | H4: 30
A5: 10123C | B5: 1 | C5: 1 | D5: 1 | E5: HEARTS WRAPPING TAPE | F5: HEARTS WRAPPING TAPE | G5: HEARTS WRAPPING TAPE | H5: 4
A6: 10123G | B6: 0 | C6: 0 | D6: 0 | G6: [multiple/absent descriptions; use code] | H6: 1
A7: 10124A | B7: 1 | C7: 1 | D7: 1 | E7: SPOTS ON RED BOOKCOVER TAPE | F7: SPOTS ON RED BOOKCOVER TAPE | G7: SPOTS ON RED BOOKCOVER TAPE | H7: 5
A8: 10124G | B8: 1 | C8: 1 | D8: 1 | E8: ARMY CAMO BOOKCOVER TAPE | F8: ARMY CAMO BOOKCOVER TAPE | G8: ARMY CAMO BOOKCOVER TAPE | H8: 4
A9: 10125 | B9: 1 | C9: 1 | D9: 1 | E9: MINI FUNKY DESIGN TAPES | F9: MINI FUNKY DESIGN TAPES | G9: MINI FUNKY DESIGN TAPES | H9: 94
A10: 10133 | B10: 2 | C10: 2 | D10: 2 | E10: COLOURING PENCILS BROWN TUBE | damaged | F10: COLOURING PENCILS BROWN TUBE | damaged | G10: [multiple/absent descriptions; use code] | H10: 200
A11: 10134 | B11: 0 | C11: 0 | D11: 0 | G11: [multiple/absent descriptions; use code] | H11: 1
A12: 10135 | B12: 1 | C12: 1 | D12: 1 | E12: COLOURING PENCILS BROWN TUBE | F12: COLOURING PENCILS BROWN TUBE | G12: COLOURING PENCILS BROWN TUBE | H12: 180
A13: 11001 | B13: 1 | C13: 1 | D13: 1 | E13: ASSTD DESIGN RACING CAR PEN | F13: ASSTD DESIGN RACING CAR PEN | G13: ASSTD DESIGN RACING CAR PEN | H13: 120
A14: 15030 | B14: 1 | C14: 1 | D14: 1 | E14: FAN BLACK FRAME | F14: FAN BLACK FRAME | G14: FAN BLACK FRAME | H14: 14
A15: 15034 | B15: 1 | C15: 1 | D15: 1 | E15: PAPER POCKET TRAVELING FAN | F15: PAPER POCKET TRAVELING FAN | G15: PAPER POCKET TRAVELING FAN | H15: 142
A16: 15036 | B16: 1 | C16: 1 | D16: 1 | E16: ASSORTED COLOURS SILK FAN | F16: ASSORTED COLOURS SILK FAN | G16: ASSORTED COLOURS SILK FAN | H16: 524
A17: 15039 | B17: 1 | C17: 1 | D17: 1 | E17: SANDALWOOD FAN | F17: SANDALWOOD FAN | G17: SANDALWOOD FAN | H17: 149
A18: 15044A | B18: 1 | C18: 1 | D18: 1 | E18: PINK PAPER PARASOL | F18: PINK PAPER PARASOL | G18: PINK PAPER PARASOL | H18: 104
A19: 15044B | B19: 1 | C19: 1 | D19: 1 | E19: BLUE PAPER PARASOL | F19: BLUE PAPER PARASOL | G19: BLUE PAPER PARASOL | H19: 62
A20: 15044C | B20: 1 | C20: 1 | D20: 1 | E20: PURPLE PAPER PARASOL | F20: PURPLE PAPER PARASOL | G20: PURPLE PAPER PARASOL | H20: 91
A21: 15044D | B21: 1 | C21: 1 | D21: 1 | E21: RED PAPER PARASOL | F21: RED PAPER PARASOL | G21: RED PAPER PARASOL | H21: 87
A22: 15056BL | B22: 1 | C22: 1 | D22: 1 | E22: EDWARDIAN PARASOL BLACK | F22: EDWARDIAN PARASOL BLACK | G22: EDWARDIAN PARASOL BLACK | H22: 326
A23: 15056N | B23: 1 | C23: 1 | D23: 1 | E23: EDWARDIAN PARASOL NATURAL | F23: EDWARDIAN PARASOL NATURAL | G23: EDWARDIAN PARASOL NATURAL | H23: 467
... A47: 16052 | B47: 1 | C47: 1 | D47: 1 | E47: TEATIME PUSH DOWN RUBBER | F47: TEATIME PUSH DOWN RUBBER | G47: TEATIME PUSH DOWN RUBBER | H47: 14
A48: 16053 | B48: 0 | C48: 0 | D48: 0 | G48: [multiple/absent descriptions; use code] | H48: 1
A49: 16054 | B49: 1 | C49: 1 | D49: 1 | E49: POPART RECT PENCIL SHARPENER ASST | F49: POPART RECT PENCIL SHARPENER ASST | G49: POPART RECT PENCIL SHARPENER ASST | H49: 34
A50: 16151A | B50: 1 | C50: 1 | D50: 1 | E50: FLOWERS HANDBAG blue and orange | F50: FLOWERS HANDBAG blue and orange | G50: FLOWERS HANDBAG blue and orange | H50: 4
A51: 16156L | B51: 2 | C51: 2 | D51: 2 | E51: WRAP CAROUSEL | WRAP, CAROUSEL | F51: WRAP CAROUSEL | WRAP, CAROUSEL | G51: [multiple/absent descriptions; use code] | H51: 18
A52: 16156S | B52: 1 | C52: 1 | D52: 1 | E52: WRAP PINK FAIRY CAKES | F52: WRAP PINK FAIRY CAKES | G52: WRAP PINK FAIRY CAKES | H52: 168
A53: 16161G | B53: 1 | C53: 1 | D53: 1 | E53: WRAP BAD HAIR DAY | F53: WRAP BAD HAIR DAY | G53: WRAP BAD HAIR DAY | H53: 22
A54: 16161M | B54: 1 | C54: 1 | D54: 1 | E54: WRAP PINK FLOCK | F54: WRAP PINK FLOCK | G54: WRAP PINK FLOCK | H54: 1
A55: 16161P | B55: 1 | C55: 1 | D55: 1 | E55: WRAP ENGLISH ROSE | F55: WRAP ENGLISH ROSE | G55: WRAP ENGLISH ROSE | H55: 250
A56: 16161U | B56: 1 | C56: 1 | D56: 1 | E56: WRAP SUKI AND FRIENDS | F56: WRAP SUKI AND FRIENDS | G56: WRAP SUKI AND FRIENDS | H56: 135
A57: 16162L | B57: 1 | C57: 1 | D57: 1 | E57: THE KING GIFT BAG | F57: THE KING GIFT BAG | G57: THE KING GIFT BAG | H57: 10
A58: 16162M | B58: 2 | C58: 2 | D58: 2 | E58: THE KING GIFT BAG 25x24x12cm | alan hodge cant mamage this section | F58: THE KING GIFT BAG 25x24x12cm | alan hodge cant mamage this section | G58: [multiple/absent descriptions; use code] | H58: 10
A59: 16168M | B59: 2 | C59: 2 | D59: 2 | E59: FUNKY MONKEY GIFT BAG MEDIUM | found | F59: FUNKY MONKEY GIFT BAG MEDIUM | found | G59: [multiple/absent descriptions; use code] | H59: 42
A60: 16169E | B60: 2 | C60: 2 | D60: 2 | E60: WRAP 50'S CHRISTMAS | check | F60: WRAP 50'S CHRISTMAS | check | G60: [multiple/absent descriptions; use code] | H60: 153
... A86: 17007B | B86: 1 | C86: 1 | D86: 1 | E86: S/3 POT POURI CUSHIONS BLUE COLOURS | F86: S/3 POT POURI CUSHIONS BLUE COLOURS | G86: S/3 POT POURI CUSHIONS BLUE COLOURS | H86: 3
A87: 17011A | B87: 0 | C87: 0 | D87: 0 | G87: [multiple/absent descriptions; use code] | H87: 1
A88: 17011F | B88: 1 | C88: 1 | D88: 1 | E88: ORIGAMI SANDLEWOOD INCENSE+FLOWER | F88: ORIGAMI SANDLEWOOD INCENSE+FLOWER | G88: ORIGAMI SANDLEWOOD INCENSE+FLOWER | H88: 8
A89: 17012A | B89: 1 | C89: 1 | D89: 1 | E89: ORIGAMI VANILLA INCENSE/CANDLE SET | F89: ORIGAMI VANILLA INCENSE/CANDLE SET | G89: ORIGAMI VANILLA INCENSE/CANDLE SET | H89: 67
A90: 17012B | B90: 2 | C90: 2 | D90: 2 | E90: ORIGAMI JASMINE INCENSE/CANDLE SET | check | F90: ORIGAMI JASMINE INCENSE/CANDLE SET | check | G90: [multiple/absent descriptions; use code] | H90: 87
A91: 17012C | B91: 2 | C91: 2 | D91: 2 | E91: ORIGAMI LAVENDER INCENSE/CANDL SET | check | F91: ORIGAMI LAVENDER INCENSE/CANDL SET | check | G91: [multiple/absent descriptions; use code] | H91: 87
A92: 17012D | B92: 1 | C92: 1 | D92: 1 | E92: ORIGAMI ROSE INCENSE/CANDLE SET | F92: ORIGAMI ROSE INCENSE/CANDLE SET | G92: ORIGAMI ROSE INCENSE/CANDLE SET | H92: 99
A93: 17012E | B93: 1 | C93: 1 | D93: 1 | E93: ORIGAMI OPIUM INCENSE/CANDLE SET | F93: ORIGAMI OPIUM INCENSE/CANDLE SET | G93: ORIGAMI OPIUM INCENSE/CANDLE SET | H93: 11
A94: 17012F | B94: 2 | C94: 2 | D94: 2 | E94: ORIGAMI SANDLEWOOD INCENSE/CAND SET | check | F94: ORIGAMI SANDLEWOOD INCENSE/CAND SET | check | G94: [multiple/absent descriptions; use code] | H94: 95
A95: 17013D | B95: 1 | C95: 1 | D95: 1 | E95: ORIGAMI ROSE INCENSE IN TUBE | F95: ORIGAMI ROSE INCENSE IN TUBE | G95: ORIGAMI ROSE INCENSE IN TUBE | H95: 15
A96: 17014A | B96: 1 | C96: 1 | D96: 1 | E96: ORIGAMI VANILLA INCENSE CONES | F96: ORIGAMI VANILLA INCENSE CONES | G96: ORIGAMI VANILLA INCENSE CONES | H96: 9
A97: 17021 | B97: 1 | C97: 1 | D97: 1 | E97: NAMASTE SWAGAT INCENSE | F97: NAMASTE SWAGAT INCENSE | G97: NAMASTE SWAGAT INCENSE | H97: 57
A98: 17028J | B98: 1 | C98: 1 | D98: 1 | E98: INCENSE BAZAAR PEACH | F98: INCENSE BAZAAR PEACH | G98: INCENSE BAZAAR PEACH | H98: 1
A99: 17038 | B99: 1 | C99: 1 | D99: 1 | E99: PORCELAIN BUDAH INCENSE HOLDER | F99: PORCELAIN BUDAH INCENSE HOLDER | G99: PORCELAIN BUDAH INCENSE HOLDER | H99: 34
... A158: 20686 | B158: 1 | C158: 1 | D158: 1 | E158: DOLLY MIXTURE CHILDREN'S UMBRELLA | F158: DOLLY MIXTURE CHILDREN'S UMBRELLA | G158: DOLLY MIXTURE CHILDREN'S UMBRELLA | H158: 79
A159: 20689 | B159: 0 | C159: 0 | D159: 0 | G159: [multiple/absent descriptions; use code] | H159: 1
A160: 20694 | B160: 2 | C160: 2 | D160: 2 | E160: ? | FLORAL PINK MONSTER | F160: ? | FLORAL PINK MONSTER | G160: [multiple/absent descriptions; use code] | H160: 18
A161: 20695 | B161: 1 | C161: 1 | D161: 1 | E161: FLORAL BLUE MONSTER | F161: FLORAL BLUE MONSTER | G161: FLORAL BLUE MONSTER | H161: 4
A162: 20696 | B162: 1 | C162: 1 | D162: 1 | E162: FLORAL SOFT CAR TOY | F162: FLORAL SOFT CAR TOY | G162: FLORAL SOFT CAR TOY | H162: 30
A163: 20697 | B163: 1 | C163: 1 | D163: 1 | E163: LITTLE GREEN MONSTER SOFT TOY | F163: LITTLE GREEN MONSTER SOFT TOY | G163: LITTLE GREEN MONSTER SOFT TOY | H163: 13
A164: 20698 | B164: 1 | C164: 1 | D164: 1 | E164: LITTLE PINK MONSTER SOFT TOY | F164: LITTLE PINK MONSTER SOFT TOY | G164: LITTLE PINK MONSTER SOFT TOY | H164: 9
A165: 20699 | B165: 1 | C165: 1 | D165: 1 | E165: MOUSEY LONG LEGS SOFT TOY | F165: MOUSEY LONG LEGS SOFT TOY | G165: MOUSEY LONG LEGS SOFT TOY | H165: 42
A166: 20700 | B166: 2 | C166: 2 | D166: 2 | E166: ? | GREEN CAT FLORAL CUSHION COVER | F166: ? | GREEN CAT FLORAL CUSHION COVER | G166: [multiple/absent descriptions; use code] | H166: 55
A167: 20701 | B167: 1 | C167: 1 | D167: 1 | E167: PINK CAT FLORAL CUSHION COVER | F167: PINK CAT FLORAL CUSHION COVER | G167: PINK CAT FLORAL CUSHION COVER | H167: 20
A168: 20702 | B168: 1 | C168: 1 | D168: 1 | E168: PINK PADDED MOBILE | F168: PINK PADDED MOBILE | G168: PINK PADDED MOBILE | H168: 44
A169: 20703 | B169: 1 | C169: 1 | D169: 1 | E169: BLUE PADDED SOFT MOBILE | F169: BLUE PADDED SOFT MOBILE | G169: BLUE PADDED SOFT MOBILE | H169: 4
A170: 20704 | B170: 1 | C170: 1 | D170: 1 | E170: MR ROBOT SOFT TOY | F170: MR ROBOT SOFT TOY | G170: MR ROBOT SOFT TOY | H170: 45
A171: 20705 | B171: 1 | C171: 1 | D171: 1 | E171: MRS ROBOT SOFT TOY | F171: MRS ROBOT SOFT TOY | G171: MRS ROBOT SOFT TOY | H171: 29
... A189: 20735 | B189: 1 | C189: 1 | D189: 1 | E189: BLACK MINI TAPE MEASURE | F189: BLACK MINI TAPE MEASURE | G189: BLACK MINI TAPE MEASURE | H189: 114
A190: 20738 | B190: 0 | C190: 0 | D190: 0 | G190: [multiple/absent descriptions; use code] | H190: 1
A191: 20748 | B191: 2 | C191: 2 | D191: 2 | E191: Found | KENSINGTON COFFEE SET | F191: Found | KENSINGTON COFFEE SET | G191: [multiple/absent descriptions; use code] | H191: 36
A192: 20749 | B192: 1 | C192: 1 | D192: 1 | E192: ASSORTED COLOUR MINI CASES | F192: ASSORTED COLOUR MINI CASES | G192: ASSORTED COLOUR MINI CASES | H192: 394
A193: 20750 | B193: 1 | C193: 1 | D193: 1 | E193: RED RETROSPOT MINI CASES | F193: RED RETROSPOT MINI CASES | G193: RED RETROSPOT MINI CASES | H193: 391
A194: 20751 | B194: 2 | C194: 2 | D194: 2 | E194: FUNKY WASHING UP GLOVES ASSORTED | check | F194: FUNKY WASHING UP GLOVES ASSORTED | check | G194: [multiple/absent descriptions; use code] | H194: 226
A195: 20752 | B195: 2 | C195: 2 | D195: 2 | E195: BLUE POLKADOT WASHING UP GLOVES | check | F195: BLUE POLKADOT WASHING UP GLOVES | check | G195: [multiple/absent descriptions; use code] | H195: 154
A196: 20754 | B196: 2 | C196: 2 | D196: 2 | E196: Found | RETROSPOT RED WASHING UP GLOVES | F196: Found | RETROSPOT RED WASHING UP GLOVES | G196: [multiple/absent descriptions; use code] | H196: 310
A197: 20755 | B197: 1 | C197: 1 | D197: 1 | E197: BLUE PAISLEY POCKET BOOK | F197: BLUE PAISLEY POCKET BOOK | G197: BLUE PAISLEY POCKET BOOK | H197: 63
A198: 20756 | B198: 1 | C198: 1 | D198: 1 | E198: GREEN FERN POCKET BOOK | F198: GREEN FERN POCKET BOOK | G198: GREEN FERN POCKET BOOK | H198: 23
A199: 20757 | B199: 1 | C199: 1 | D199: 1 | E199: RED DAISY POCKET BOOK | F199: RED DAISY POCKET BOOK | G199: RED DAISY POCKET BOOK | H199: 36
A200: 20758 | B200: 1 | C200: 1 | D200: 1 | E200: ABSTRACT CIRCLES POCKET BOOK | F200: ABSTRACT CIRCLES POCKET BOOK | G200: ABSTRACT CIRCLES POCKET BOOK | H200: 46
A201: 20759 | B201: 1 | C201: 1 | D201: 1 | E201: CHRYSANTHEMUM POCKET BOOK | F201: CHRYSANTHEMUM POCKET BOOK | G201: CHRYSANTHEMUM POCKET BOOK | H201: 21
A202: 20760 | B202: 1 | C202: 1 | D202: 1 | E202: GARDEN PATH POCKET BOOK | F202: GARDEN PATH POCKET BOOK | G202: GARDEN PATH POCKET BOOK | H202: 23
... A237: 20823 | B237: 1 | C237: 1 | D237: 1 | E237: GOLD WINE GOBLET | F237: GOLD WINE GOBLET | G237: GOLD WINE GOBLET | H237: 10
A238: 20825 | B238: 0 | C238: 0 | D238: 0 | G238: [multiple/absent descriptions; use code] | H238: 1
A239: 20826 | B239: 1 | C239: 1 | D239: 1 | E239: SILVER APERITIF GLASS | F239: SILVER APERITIF GLASS | G239: SILVER APERITIF GLASS | H239: 10
A240: 20827 | B240: 2 | C240: 2 | D240: 2 | E240: GOLD APERITIF GLASS | damages | F240: GOLD APERITIF GLASS | damages | G240: [multiple/absent descriptions; use code] | H240: 3
A241: 20828 | B241: 1 | C241: 1 | D241: 1 | E241: GLITTER BUTTERFLY CLIPS | F241: GLITTER BUTTERFLY CLIPS | G241: GLITTER BUTTERFLY CLIPS | H241: 250
A242: 20829 | B242: 1 | C242: 1 | D242: 1 | E242: GLITTER HANGING BUTTERFLY STRING | F242: GLITTER HANGING BUTTERFLY STRING | G242: GLITTER HANGING BUTTERFLY STRING | H242: 206
A243: 20830 | B243: 1 | C243: 1 | D243: 1 | E243: SILVER PHOTO FRAME | F243: SILVER PHOTO FRAME | G243: SILVER PHOTO FRAME | H243: 38
A244: 20831 | B244: 1 | C244: 1 | D244: 1 | E244: GOLD PHOTO FRAME | F244: GOLD PHOTO FRAME | G244: GOLD PHOTO FRAME | H244: 39
A245: 20832 | B245: 2 | C245: 2 | D245: 2 | E245: RED FLOCK LOVE HEART PHOTO FRAME | check | F245: RED FLOCK LOVE HEART PHOTO FRAME | check | G245: [multiple/absent descriptions; use code] | H245: 86
A246: 20835 | B246: 1 | C246: 1 | D246: 1 | E246: FRENCH LATTICE CUSHION COVER | F246: FRENCH LATTICE CUSHION COVER | G246: FRENCH LATTICE CUSHION COVER | H246: 8
A247: 20836 | B247: 1 | C247: 1 | D247: 1 | E247: FRENCH PAISLEY CUSHION COVER | F247: FRENCH PAISLEY CUSHION COVER | G247: FRENCH PAISLEY CUSHION COVER | H247: 18
A248: 20837 | B248: 1 | C248: 1 | D248: 1 | E248: FRENCH FLORAL CUSHION COVER | F248: FRENCH FLORAL CUSHION COVER | G248: FRENCH FLORAL CUSHION COVER | H248: 15
A249: 20838 | B249: 1 | C249: 1 | D249: 1 | E249: FRENCH LATTICE CUSHION COVER | F249: FRENCH LATTICE CUSHION COVER | G249: FRENCH LATTICE CUSHION COVER | H249: 58
A250: 20839 | B250: 2 | C250: 2 | D250: 2 | E250: FRENCH PAISLEY CUSHION COVER | damages | F250: FRENCH PAISLEY CUSHION COVER | damages | G250: [multiple/absent descriptions; use code] | H250: 106
... A255: 20848 | B255: 1 | C255: 1 | D255: 1 | E255: ZINC HEART LATTICE CHARGER SMALL | F255: ZINC HEART LATTICE CHARGER SMALL | G255: ZINC HEART LATTICE CHARGER SMALL | H255: 8
A256: 20849 | B256: 0 | C256: 0 | D256: 0 | G256: [multiple/absent descriptions; use code] | H256: 1
A257: 20850 | B257: 0 | C257: 0 | D257: 0 | G257: [multiple/absent descriptions; use code] | H257: 1
A258: 20851 | B258: 1 | C258: 1 | D258: 1 | E258: ZINC HEART LATTICE TRAY OVAL | F258: ZINC HEART LATTICE TRAY OVAL | G258: ZINC HEART LATTICE TRAY OVAL | H258: 8
A259: 20854 | B259: 1 | C259: 1 | D259: 1 | E259: BLUE PATCH PURSE PINK HEART | F259: BLUE PATCH PURSE PINK HEART | G259: BLUE PATCH PURSE PINK HEART | H259: 45
A260: 20856 | B260: 2 | C260: 2 | D260: 2 | E260: ?? | DENIM PATCH PURSE PINK BUTTERFLY | F260: ?? | DENIM PATCH PURSE PINK BUTTERFLY | G260: [multiple/absent descriptions; use code] | H260: 63
A261: 20857 | B261: 1 | C261: 1 | D261: 1 | E261: BLUE ROSE PATCH PURSE PINK BUTTERFL | F261: BLUE ROSE PATCH PURSE PINK BUTTERFL | G261: BLUE ROSE PATCH PURSE PINK BUTTERFL | H261: 10
...

Sheet SpecialOperations
A1: StockCode | B1: Category | C1: Rows | D1: SignedGBP | E1: SourceRowExample
A2: AMAZONFEE | B2: PlatformFee | C2: 34 | D2: -221520.5 | E2: 14516
A3: B | B3: AccountingAdjustment | C3: 3 | D3: -11062.06 | E3: 299984
A4: BANK CHARGES | B4: BankFee | C4: 37 | D4: -7175.639 | E4: 4408
A5: C2 | B5: Logistics | C5: 144 | D5: 6986 | E5: 1425
A6: CRUK | B6: Commission | C6: 16 | D6: -7933.43 | E6: 317510
A7: D | B7: Discount | C7: 77 | D7: -5696.22 | E7: 143
A8: DOT | B8: Logistics | C8: 710 | D8: 206245.48 | E8: 1816
A9: M | B9: Manual | C9: 571 | D9: -68674.19 | E9: 2241
A10: POST | B10: Logistics | C10: 1256 | D10: 66230.64 | E10: 47
A11: S | B11: Sample | C11: 63 | D11: -3049.39 | E11: 14438
A12: gift_0001_10 | B12: Voucher | C12: 9 | D12: 74.97 | E12: 112444
A13: gift_0001_20 | B13: Voucher | C13: 10 | D13: 167.05 | E13: 44796
... A17: m | B17: Manual | C17: 1 | D17: 2.55 | E17: 40385

Sheet Customers
A1: CustomerID | B1: SalesRows | C1: SalesGBP | D1: SalesInvoiceIDs
A2: 12346 | B2: 1 | C2: 77183.6 | D2: 1
A3: 12347 | B3: 182 | C3: 4310 | D3: 7
A4: 12348 | B4: 27 | C4: 1437.24 | D4: 4
A5: 12349 | B5: 72 | C5: 1457.55 | D5: 1
A6: 12350 | B6: 16 | C6: 294.4 | D6: 1
A7: 12352 | B7: 77 | C7: 1385.74 | D7: 7
A8: 12353 | B8: 4 | C8: 89 | D8: 1
A9: 12354 | B9: 58 | C9: 1079.4 | D9: 1
A10: 12355 | B10: 13 | C10: 459.4 | D10: 1
A11: 12356 | B11: 58 | C11: 2487.43 | D11: 3
A12: 12357 | B12: 131 | C12: 6207.67 | D12: 1
A13: 12358 | B13: 17 | C13: 928.06 | D13: 2
... A4335: 18287 | B4335: 70 | C4335: 1837.28 | D4335: 3

Sheet ReviewExamples
A1: SourceFile | B1: SourceSheet | C1: SourceRow | D1: InvoiceNo_Raw | E1: StockCode_Raw | F1: Description_Raw | G1: Quantity_Raw | H1: InvoiceDate_Raw | I1: UnitPrice_Raw | J1: CustomerID_Raw | K1: Country_Raw | L1: RecordID | M1: InvoiceNo | N1: StockCode | O1: CustomerID | P1: DescriptionTrim | Q1: Quantity | R1: UnitPrice | S1: InvoiceDate | T1: Country | U1: Month | V1: PriceUnits4 | W1: AmountUnits4 | X1: LineAmount | Y1: HasMissingCustomer | Z1: HasMissingDescription | AA1: HasNonTextDescription | AB1: HasOuterWhitespace | AC1: IsExactDuplicateMember | AD1: IsDuplicateBeyondFirst | AE1: IsDescriptionVariantDuplicate | AF1: DescriptionVariantCount | AG1: HasMultipleDescriptions | AH1: CodeCategory | AI1: IsUnmappedCode | AJ1: IsCancellationCode | AK1: IsInvoicePatternException | AL1: IsNonCNegative | AM1: IsZeroPrice | AN1: IsNegativePrice | AO1: IsLargeAmount | AP1: TransactionClass | AQ1: ReportScope | AR1: CustomerAnalysisEligible | AS1: NeedsReview | AT1: ReviewReasons | AU1: ExampleReason
A2: Online Retail.xlsx | B2: Online Retail | C2: 624 | D2: 536414 | E2: 22139 | G2: 56 | H2: 40513.494 | I2: 0 | K2: United Kingdom | L2: Online Retail.xlsx|Online Retail|000000624 | M2: 536414 | N2: 22139 | Q2: 56 | R2: 0 | S2: 40513.494 | T2: United Kingdom | U2: 2010-12 | V2: 0 | W2: 0 | X2: 0 | Y2: TRUE | Z2: TRUE | AA2: FALSE | AB2: FALSE | AC2: FALSE | AD2: FALSE | AE2: FALSE | AF2: 2 | AG2: TRUE | AH2: Merchandise | AI2: FALSE | AJ2: FALSE | AK2: FALSE | AL2: FALSE | AM2: TRUE | AN2: FALSE | AO2: FALSE | AP2: UnresolvedReview | AQ2: FALSE | AR2: FALSE | AS2: TRUE | AT2: Missing customer ID; Missing description; Code with multiple descriptions; Zero price; Unresolved transaction class | AU2: HasMissingCustomer
A3: Online Retail.xlsx | B3: Online Retail | C3: 1445 | D3: 536544 | E3: 21773 | F3: DECORATIVE ROSE BATHROOM BOTTLE | G3: 1 | H3: 40513.606 | I3: 2.51 | K3: United Kingdom | L3: Online Retail.xlsx|Online Retail|000001445 | M3: 536544 | N3: 21773 | P3: DECORATIVE ROSE BATHROOM BOTTLE | Q3: 1 | R3: 2.51 | S3: 40513.606 | T3: United Kingdom | U3: 2010-12 | V3: 25100 | W3: 25100 | X3: 2.51 | Y3: TRUE | Z3: FALSE | AA3: FALSE | AB3: FALSE | AC3: FALSE | AD3: FALSE | AE3: FALSE | AF3: 1 | AG3: FALSE | AH3: Merchandise | AI3: FALSE | AJ3: FALSE | AK3: FALSE | AL3: FALSE | AM3: FALSE | AN3: FALSE | AO3: FALSE | AP3: MerchandiseSale | AQ3: TRUE | AR3: FALSE | AS3: TRUE | AT3: Missing customer ID | AU3: HasMissingCustomer
A4: Online Retail.xlsx | B4: Online Retail | C4: 1446 | D4: 536544 | E4: 21774 | F4: DECORATIVE CATS BATHROOM BOTTLE | G4: 2 | H4: 40513.606 | I4: 2.51 | K4: United Kingdom | L4: Online Retail.xlsx|Online Retail|000001446 | M4: 536544 | N4: 21774 | P4: DECORATIVE CATS BATHROOM BOTTLE | Q4: 2 | R4: 2.51 | S4: 40513.606 | T4: United Kingdom | U4: 2010-12 | V4: 25100 | W4: 50200 | X4: 5.02 | Y4: TRUE | Z4: FALSE | AA4: FALSE | AB4: FALSE | AC4: FALSE | AD4: FALSE | AE4: FALSE | AF4: 1 | AG4: FALSE | AH4: Merchandise | AI4: FALSE | AJ4: FALSE | AK4: FALSE | AL4: FALSE | AM4: FALSE | AN4: FALSE | AO4: FALSE | AP4: MerchandiseSale | AQ4: TRUE | AR4: FALSE | AS4: TRUE | AT4: Missing customer ID | AU4: HasMissingCustomer
A5: Online Retail.xlsx | B5: Online Retail | C5: 1447 | D5: 536544 | E5: 21786 | F5: POLKADOT RAIN HAT | G5: 4 | H5: 40513.606 | I5: 0.85 | K5: United Kingdom | L5: Online Retail.xlsx|Online Retail|000001447 | M5: 536544 | N5: 21786 | P5: POLKADOT RAIN HAT | Q5: 4 | R5: 0.85 | S5: 40513.606 | T5: United Kingdom | U5: 2010-12 | V5: 8500 | W5: 34000 | X5: 3.4 | Y5: TRUE | Z5: FALSE | AA5: FALSE | AB5: TRUE | AC5: FALSE | AD5: FALSE | AE5: FALSE | AF5: 2 | AG5: TRUE | AH5: Merchandise | AI5: FALSE | AJ5: FALSE | AK5: FALSE | AL5: FALSE | AM5: FALSE | AN5: FALSE | AO5: FALSE | AP5: MerchandiseSale | AQ5: TRUE | AR5: FALSE | AS5: TRUE | AT5: Missing customer ID; Code with multiple descriptions | AU5: HasMissingCustomer
A6: Online Retail.xlsx | B6: Online Retail | C6: 1448 | D6: 536544 | E6: 21787 | F6: RAIN PONCHO RETROSPOT | G6: 2 | H6: 40513.606 | I6: 1.66 | K6: United Kingdom | L6: Online Retail.xlsx|Online Retail|000001448 | M6: 536544 | N6: 21787 | P6: RAIN PONCHO RETROSPOT | Q6: 2 | R6: 1.66 | S6: 40513.606 | T6: United Kingdom | U6: 2010-12 | V6: 16600 | W6: 33200 | X6: 3.32 | Y6: TRUE | Z6: FALSE | AA6: FALSE | AB6: FALSE | AC6: FALSE | AD6: FALSE | AE6: FALSE | AF6: 1 | AG6: FALSE | AH6: Merchandise | AI6: FALSE | AJ6: FALSE | AK6: FALSE | AL6: FALSE | AM6: FALSE | AN6: FALSE | AO6: FALSE | AP6: MerchandiseSale | AQ6: TRUE | AR6: FALSE | AS6: TRUE | AT6: Missing customer ID | AU6: HasMissingCustomer
A7: Online Retail.xlsx | B7: Online Retail | C7: 1449 | D7: 536544 | E7: 21790 | F7: VINTAGE SNAP CARDS | G7: 9 | H7: 40513.606 | I7: 1.66 | K7: United Kingdom | L7: Online Retail.xlsx|Online Retail|000001449 | M7: 536544 | N7: 21790 | P7: VINTAGE SNAP CARDS | Q7: 9 | R7: 1.66 | S7: 40513.606 | T7: United Kingdom | U7: 2010-12 | V7: 16600 | W7: 149400 | X7: 14.94 | Y7: TRUE | Z7: FALSE | AA7: FALSE | AB7: FALSE | AC7: FALSE | AD7: FALSE | AE7: FALSE | AF7: 1 | AG7: FALSE | AH7: Merchandise | AI7: FALSE | AJ7: FALSE | AK7: FALSE | AL7: FALSE | AM7: FALSE | AN7: FALSE | AO7: FALSE | AP7: MerchandiseSale | AQ7: TRUE | AR7: FALSE | AS7: TRUE | AT7: Missing customer ID | AU7: HasMissingCustomer
A8: Online Retail.xlsx | B8: Online Retail | C8: 1450 | D8: 536544 | E8: 21791 | F8: VINTAGE HEADS AND TAILS CARD GAME | G8: 2 | H8: 40513.606 | I8: 2.51 | K8: United Kingdom | L8: Online Retail.xlsx|Online Retail|000001450 | M8: 536544 | N8: 21791 | P8: VINTAGE HEADS AND TAILS CARD GAME | Q8: 2 | R8: 2.51 | S8: 40513.606 | T8: United Kingdom | U8: 2010-12 | V8: 25100 | W8: 50200 | X8: 5.02 | Y8: TRUE | Z8: FALSE | AA8: FALSE | AB8: TRUE | AC8: FALSE | AD8: FALSE | AE8: FALSE | AF8: 1 | AG8: FALSE | AH8: Merchandise | AI8: FALSE | AJ8: FALSE | AK8: FALSE | AL8: FALSE | AM8: FALSE | AN8: FALSE | AO8: FALSE | AP8: MerchandiseSale | AQ8: TRUE | AR8: FALSE | AS8: TRUE | AT8: Missing customer ID | AU8: HasMissingCustomer
A9: Online Retail.xlsx | B9: Online Retail | C9: 1451 | D9: 536544 | E9: 21801 | F9: CHRISTMAS TREE DECORATION WITH BELL | G9: 10 | H9: 40513.606 | I9: 0.43 | K9: United Kingdom | L9: Online Retail.xlsx|Online Retail|000001451 | M9: 536544 | N9: 21801 | P9: CHRISTMAS TREE DECORATION WITH BELL | Q9: 10 | R9: 0.43 | S9: 40513.606 | T9: United Kingdom | U9: 2010-12 | V9: 4300 | W9: 43000 | X9: 4.3 | Y9: TRUE | Z9: FALSE | AA9: FALSE | AB9: FALSE | AC9: FALSE | AD9: FALSE | AE9: FALSE | AF9: 1 | AG9: FALSE | AH9: Merchandise | AI9: FALSE | AJ9: FALSE | AK9: FALSE | AL9: FALSE | AM9: FALSE | AN9: FALSE | AO9: FALSE | AP9: MerchandiseSale | AQ9: TRUE | AR9: FALSE | AS9: TRUE | AT9: Missing customer ID | AU9: HasMissingCustomer
A10: Online Retail.xlsx | B10: Online Retail | C10: 624 | D10: 536414 | E10: 22139 | G10: 56 | H10: 40513.494 | I10: 0 | K10: United Kingdom | L10: Online Retail.xlsx|Online Retail|000000624 | M10: 536414 | N10: 22139 | Q10: 56 | R10: 0 | S10: 40513.494 | T10: United Kingdom | U10: 2010-12 | V10: 0 | W10: 0 | X10: 0 | Y10: TRUE | Z10: TRUE | AA10: FALSE | AB10: FALSE | AC10: FALSE | AD10: FALSE | AE10: FALSE | AF10: 2 | AG10: TRUE | AH10: Merchandise | AI10: FALSE | AJ10: FALSE | AK10: FALSE | AL10: FALSE | AM10: TRUE | AN10: FALSE | AO10: FALSE | AP10: UnresolvedReview | AQ10: FALSE | AR10: FALSE | AS10: TRUE | AT10: Missing customer ID; Missing description; Code with multiple descriptions; Zero price; Unresolved transaction class | AU10: HasMissingDescription
A11: Online Retail.xlsx | B11: Online Retail | C11: 1972 | D11: 536545 | E11: 21134 | G11: 1 | H11: 40513.606 | I11: 0 | K11: United Kingdom | L11: Online Retail.xlsx|Online Retail|000001972 | M11: 536545 | N11: 21134 | Q11: 1 | R11: 0 | S11: 40513.606 | T11: United Kingdom | U11: 2010-12 | V11: 0 | W11: 0 | X11: 0 | Y11: TRUE | Z11: TRUE | AA11: FALSE | AB11: FALSE | AC11: FALSE | AD11: FALSE | AE11: FALSE | AF11: 0 | AG11: FALSE | AH11: Merchandise | AI11: FALSE | AJ11: FALSE | AK11: FALSE | AL11: FALSE | AM11: TRUE | AN11: FALSE | AO11: FALSE | AP11: UnresolvedReview | AQ11: FALSE | AR11: FALSE | AS11: TRUE | AT11: Missing customer ID; Missing description; Zero price; Unresolved transaction class | AU11: HasMissingDescription
A12: Online Retail.xlsx | B12: Online Retail | C12: 1973 | D12: 536546 | E12: 22145 | G12: 1 | H12: 40513.606 | I12: 0 | K12: United Kingdom | L12: Online Retail.xlsx|Online Retail|000001973 | M12: 536546 | N12: 22145 | Q12: 1 | R12: 0 | S12: 40513.606 | T12: United Kingdom | U12: 2010-12 | V12: 0 | W12: 0 | X12: 0 | Y12: TRUE | Z12: TRUE | AA12: FALSE | AB12: FALSE | AC12: FALSE | AD12: FALSE | AE12: FALSE | AF12: 1 | AG12: FALSE | AH12: Merchandise | AI12: FALSE | AJ12: FALSE | AK12: FALSE | AL12: FALSE | AM12: TRUE | AN12: FALSE | AO12: FALSE | AP12: UnresolvedReview | AQ12: FALSE | AR12: FALSE | AS12: TRUE | AT12: Missing customer ID; Missing description; Zero price; Unresolved transaction class | AU12: HasMissingDescription
A13: Online Retail.xlsx | B13: Online Retail | C13: 1974 | D13: 536547 | E13: 37509 | G13: 1 | H13: 40513.606 | I13: 0 | K13: United Kingdom | L13: Online Retail.xlsx|Online Retail|000001974 | M13: 536547 | N13: 37509 | Q13: 1 | R13: 0 | S13: 40513.606 | T13: United Kingdom | U13: 2010-12 | V13: 0 | W13: 0 | X13: 0 | Y13: TRUE | Z13: TRUE | AA13: FALSE | AB13: FALSE | AC13: FALSE | AD13: FALSE | AE13: FALSE | AF13: 1 | AG13: FALSE | AH13: Merchandise | AI13: FALSE | AJ13: FALSE | AK13: FALSE | AL13: FALSE | AM13: TRUE | AN13: FALSE | AO13: FALSE | AP13: UnresolvedReview | AQ13: FALSE | AR13: FALSE | AS13: TRUE | AT13: Missing customer ID; Missing description; Zero price; Unresolved transaction class | AU13: HasMissingDescription
A14: Online Retail.xlsx | B14: Online Retail | C14: 1989 | D14: 536549 | E14: 85226A | G14: 1 | H14: 40513.607 | I14: 0 | K14: United Kingdom | L14: Online Retail.xlsx|Online Retail|000001989 | M14: 536549 | N14: 85226A | Q14: 1 | R14: 0 | S14: 40513.607 | T14: United Kingdom | U14: 2010-12 | V14: 0 | W14: 0 | X14: 0 | Y14: TRUE | Z14: TRUE | AA14: FALSE | AB14: FALSE | AC14: FALSE | AD14: FALSE | AE14: FALSE | AF14: 0 | AG14: FALSE | AH14: Merchandise | AI14: FALSE | AJ14: FALSE | AK14: FALSE | AL14: FALSE | AM14: TRUE | AN14: FALSE | AO14: FALSE | AP14: UnresolvedReview | AQ14: FALSE | AR14: FALSE | AS14: TRUE | AT14: Missing customer ID; Missing description; Zero price; Unresolved transaction class | AU14: HasMissingDescription
A15: Online Retail.xlsx | B15: Online Retail | C15: 1990 | D15: 536550 | E15: 85044 | G15: 1 | H15: 40513.607 | I15: 0 | K15: United Kingdom | L15: Online Retail.xlsx|Online Retail|000001990 | M15: 536550 | N15: 85044 | Q15: 1 | R15: 0 | S15: 40513.607 | T15: United Kingdom | U15: 2010-12 | V15: 0 | W15: 0 | X15: 0 | Y15: TRUE | Z15: TRUE | AA15: FALSE | AB15: FALSE | AC15: FALSE | AD15: FALSE | AE15: FALSE | AF15: 0 | AG15: FALSE | AH15: Merchandise | AI15: FALSE | AJ15: FALSE | AK15: FALSE | AL15: FALSE | AM15: TRUE | AN15: FALSE | AO15: FALSE | AP15: UnresolvedReview | AQ15: FALSE | AR15: FALSE | AS15: TRUE | AT15: Missing customer ID; Missing description; Zero price; Unresolved transaction class | AU15: HasMissingDescription
A16: Online Retail.xlsx | B16: Online Retail | C16: 2026 | D16: 536552 | E16: 20950 | G16: 1 | H16: 40513.607 | I16: 0 | K16: United Kingdom | L16: Online Retail.xlsx|Online Retail|000002026 | M16: 536552 | N16: 20950 | Q16: 1 | R16: 0 | S16: 40513.607 | T16: United Kingdom | U16: 2010-12 | V16: 0 | W16: 0 | X16: 0 | Y16: TRUE | Z16: TRUE | AA16: FALSE | AB16: FALSE | AC16: FALSE | AD16: FALSE | AE16: FALSE | AF16: 0 | AG16: FALSE | AH16: Merchandise | AI16: FALSE | AJ16: FALSE | AK16: FALSE | AL16: FALSE | AM16: TRUE | AN16: FALSE | AO16: FALSE | AP16: UnresolvedReview | AQ16: FALSE | AR16: FALSE | AS16: TRUE | AT16: Missing customer ID; Missing description; Zero price; Unresolved transaction class | AU16: HasMissingDescription
A17: Online Retail.xlsx | B17: Online Retail | C17: 2027 | D17: 536553 | E17: 37461 | G17: 3 | H17: 40513.608 | I17: 0 | K17: United Kingdom | L17: Online Retail.xlsx|Online Retail|000002027 | M17: 536553 | N17: 37461 | Q17: 3 | R17: 0 | S17: 40513.608 | T17: United Kingdom | U17: 2010-12 | V17: 0 | W17: 0 | X17: 0 | Y17: TRUE | Z17: TRUE | AA17: FALSE | AB17: FALSE | AC17: FALSE | AD17: FALSE | AE17: FALSE | AF17: 1 | AG17: FALSE | AH17: Merchandise | AI17: FALSE | AJ17: FALSE | AK17: FALSE | AL17: FALSE | AM17: TRUE | AN17: FALSE | AO17: FALSE | AP17: UnresolvedReview | AQ17: FALSE | AR17: FALSE | AS17: TRUE | AT17: Missing customer ID; Missing description; Zero price; Unresolved transaction class | AU17: HasMissingDescription
A18: Online Retail.xlsx | B18: Online Retail | C18: 420393 | D18: 572891 | E18: 23343 | F18: 20713 | G18: -400 | H18: 40842.593 | I18: 0 | K18: United Kingdom | L18: Online Retail.xlsx|Online Retail|000420393 | M18: 572891 | N18: 23343 | Q18: -400 | R18: 0 | S18: 40842.593 | T18: United Kingdom | U18: 2011-10 | V18: 0 | W18: 0 | X18: 0 | Y18: TRUE | Z18: FALSE | AA18: TRUE | AB18: FALSE | AC18: FALSE | AD18: FALSE | AE18: FALSE | AF18: 4 | AG18: TRUE | AH18: Merchandise | AI18: FALSE | AJ18: FALSE | AK18: FALSE | AL18: TRUE | AM18: TRUE | AN18: FALSE | AO18: FALSE | AP18: UnresolvedReview | AQ18: FALSE | AR18: FALSE | AS18: TRUE | AT18: Missing customer ID; Non-text description; Code with multiple descriptions; Negative quantity without C; Zero price; Unresolved transaction class | AU18: HasNonTextDescription
A19: Online Retail.xlsx | B19: Online Retail | C19: 487 | D19: 536409 | E19: 22111 | F19: SCOTTIE DOG HOT WATER BOTTLE | G19: 1 | H19: 40513.49 | I19: 4.95 | J19: 17908 | K19: United Kingdom | L19: Online Retail.xlsx|Online Retail|000000487 | M19: 536409 | N19: 22111 | O19: 17908 | P19: SCOTTIE DOG HOT WATER BOTTLE | Q19: 1 | R19: 4.95 | S19: 40513.49 | T19: United Kingdom | U19: 2010-12 | V19: 49500 | W19: 49500 | X19: 4.95 | Y19: FALSE | Z19: FALSE | AA19: FALSE | AB19: FALSE | AC19: TRUE | AD19: FALSE | AE19: FALSE | AF19: 1 | AG19: FALSE | AH19: Merchandise | AI19: FALSE | AJ19: FALSE | AK19: FALSE | AL19: FALSE | AM19: FALSE | AN19: FALSE | AO19: FALSE | AP19: MerchandiseSale | AQ19: TRUE | AR19: TRUE | AS19: TRUE | AT19: Exact duplicate group member | AU19: IsExactDuplicateMember
A20: Online Retail.xlsx | B20: Online Retail | C20: 491 | D20: 536409 | E20: 22866 | F20: HAND WARMER SCOTTY DOG DESIGN | G20: 1 | H20: 40513.49 | I20: 2.1 | J20: 17908 | K20: United Kingdom | L20: Online Retail.xlsx|Online Retail|000000491 | M20: 536409 | N20: 22866 | O20: 17908 | P20: HAND WARMER SCOTTY DOG DESIGN | Q20: 1 | R20: 2.1 | S20: 40513.49 | T20: United Kingdom | U20: 2010-12 | V20: 21000 | W20: 21000 | X20: 2.1 | Y20: FALSE | Z20: FALSE | AA20: FALSE | AB20: FALSE | AC20: TRUE | AD20: FALSE | AE20: FALSE | AF20: 1 | AG20: FALSE | AH20: Merchandise | AI20: FALSE | AJ20: FALSE | AK20: FALSE | AL20: FALSE | AM20: FALSE | AN20: FALSE | AO20: FALSE | AP20: MerchandiseSale | AQ20: TRUE | AR20: TRUE | AS20: TRUE | AT20: Exact duplicate group member | AU20: IsExactDuplicateMember
A21: Online Retail.xlsx | B21: Online Retail | C21: 496 | D21: 536409 | E21: 21866 | F21: UNION JACK FLAG LUGGAGE TAG | G21: 1 | H21: 40513.49 | I21: 1.25 | J21: 17908 | K21: United Kingdom | L21: Online Retail.xlsx|Online Retail|000000496 | M21: 536409 | N21: 21866 | O21: 17908 | P21: UNION JACK FLAG LUGGAGE TAG | Q21: 1 | R21: 1.25 | S21: 40513.49 | T21: United Kingdom | U21: 2010-12 | V21: 12500 | W21: 12500 | X21: 1.25 | Y21: FALSE | Z21: FALSE | AA21: FALSE | AB21: FALSE | AC21: TRUE | AD21: FALSE | AE21: FALSE | AF21: 1 | AG21: FALSE | AH21: Merchandise | AI21: FALSE | AJ21: FALSE | AK21: FALSE | AL21: FALSE | AM21: FALSE | AN21: FALSE | AO21: FALSE | AP21: MerchandiseSale | AQ21: TRUE | AR21: TRUE | AS21: TRUE | AT21: Exact duplicate group member | AU21: IsExactDuplicateMember
A22: Online Retail.xlsx | B22: Online Retail | C22: 519 | D22: 536409 | E22: 21866 | F22: UNION JACK FLAG LUGGAGE TAG | G22: 1 | H22: 40513.49 | I22: 1.25 | J22: 17908 | K22: United Kingdom | L22: Online Retail.xlsx|Online Retail|000000519 | M22: 536409 | N22: 21866 | O22: 17908 | P22: UNION JACK FLAG LUGGAGE TAG | Q22: 1 | R22: 1.25 | S22: 40513.49 | T22: United Kingdom | U22: 2010-12 | V22: 12500 | W22: 12500 | X22: 1.25 | Y22: FALSE | Z22: FALSE | AA22: FALSE | AB22: FALSE | AC22: TRUE | AD22: TRUE | AE22: FALSE | AF22: 1 | AG22: FALSE | AH22: Merchandise | AI22: FALSE | AJ22: FALSE | AK22: FALSE | AL22: FALSE | AM22: FALSE | AN22: FALSE | AO22: FALSE | AP22: MerchandiseSale | AQ22: TRUE | AR22: TRUE | AS22: TRUE | AT22: Exact duplicate group member | AU22: IsExactDuplicateMember
A23: Online Retail.xlsx | B23: Online Retail | C23: 523 | D23: 536409 | E23: 22900 | F23: SET 2 TEA TOWELS I LOVE LONDON | G23: 1 | H23: 40513.49 | I23: 2.95 | J23: 17908 | K23: United Kingdom | L23: Online Retail.xlsx|Online Retail|000000523 | M23: 536409 | N23: 22900 | O23: 17908 | P23: SET 2 TEA TOWELS I LOVE LONDON | Q23: 1 | R23: 2.95 | S23: 40513.49 | T23: United Kingdom | U23: 2010-12 | V23: 29500 | W23: 29500 | X23: 2.95 | Y23: FALSE | Z23: FALSE | AA23: FALSE | AB23: TRUE | AC23: TRUE | AD23: FALSE | AE23: FALSE | AF23: 2 | AG23: TRUE | AH23: Merchandise | AI23: FALSE | AJ23: FALSE | AK23: FALSE | AL23: FALSE | AM23: FALSE | AN23: FALSE | AO23: FALSE | AP23: MerchandiseSale | AQ23: TRUE | AR23: TRUE | AS23: TRUE | AT23: Exact duplicate group member; Code with multiple descriptions | AU23: IsExactDuplicateMember
A24: Online Retail.xlsx | B24: Online Retail | C24: 529 | D24: 536409 | E24: 22866 | F24: HAND WARMER SCOTTY DOG DESIGN | G24: 1 | H24: 40513.49 | I24: 2.1 | J24: 17908 | K24: United Kingdom | L24: Online Retail.xlsx|Online Retail|000000529 | M24: 536409 | N24: 22866 | O24: 17908 | P24: HAND WARMER SCOTTY DOG DESIGN | Q24: 1 | R24: 2.1 | S24: 40513.49 | T24: United Kingdom | U24: 2010-12 | V24: 21000 | W24: 21000 | X24: 2.1 | Y24: FALSE | Z24: FALSE | AA24: FALSE | AB24: FALSE | AC24: TRUE | AD24: TRUE | AE24: FALSE | AF24: 1 | AG24: FALSE | AH24: Merchandise | AI24: FALSE | AJ24: FALSE | AK24: FALSE | AL24: FALSE | AM24: FALSE | AN24: FALSE | AO24: FALSE | AP24: MerchandiseSale | AQ24: TRUE | AR24: TRUE | AS24: TRUE | AT24: Exact duplicate group member | AU24: IsExactDuplicateMember
A25: Online Retail.xlsx | B25: Online Retail | C25: 539 | D25: 536409 | E25: 22900 | F25: SET 2 TEA TOWELS I LOVE LONDON | G25: 1 | H25: 40513.49 | I25: 2.95 | J25: 17908 | K25: United Kingdom | L25: Online Retail.xlsx|Online Retail|000000539 | M25: 536409 | N25: 22900 | O25: 17908 | P25: SET 2 TEA TOWELS I LOVE LONDON | Q25: 1 | R25: 2.95 | S25: 40513.49 | T25: United Kingdom | U25: 2010-12 | V25: 29500 | W25: 29500 | X25: 2.95 | Y25: FALSE | Z25: FALSE | AA25: FALSE | AB25: TRUE | AC25: TRUE | AD25: TRUE | AE25: FALSE | AF25: 2 | AG25: TRUE | AH25: Merchandise | AI25: FALSE | AJ25: FALSE | AK25: FALSE | AL25: FALSE | AM25: FALSE | AN25: FALSE | AO25: FALSE | AP25: MerchandiseSale | AQ25: TRUE | AR25: TRUE | AS25: TRUE | AT25: Exact duplicate group member; Code with multiple descriptions | AU25: IsExactDuplicateMember
A26: Online Retail.xlsx | B26: Online Retail | C26: 541 | D26: 536409 | E26: 22111 | F26: SCOTTIE DOG HOT WATER BOTTLE | G26: 1 | H26: 40513.49 | I26: 4.95 | J26: 17908 | K26: United Kingdom | L26: Online Retail.xlsx|Online Retail|000000541 | M26: 536409 | N26: 22111 | O26: 17908 | P26: SCOTTIE DOG HOT WATER BOTTLE | Q26: 1 | R26: 4.95 | S26: 40513.49 | T26: United Kingdom | U26: 2010-12 | V26: 49500 | W26: 49500 | X26: 4.95 | Y26: FALSE | Z26: FALSE | AA26: FALSE | AB26: FALSE | AC26: TRUE | AD26: TRUE | AE26: FALSE | AF26: 1 | AG26: FALSE | AH26: Merchandise | AI26: FALSE | AJ26: FALSE | AK26: FALSE | AL26: FALSE | AM26: FALSE | AN26: FALSE | AO26: FALSE | AP26: MerchandiseSale | AQ26: TRUE | AR26: TRUE | AS26: TRUE | AT26: Exact duplicate group member | AU26: IsExactDuplicateMember
A27: Online Retail.xlsx | B27: Online Retail | C27: 199126 | D27: 554084 | E27: 23298 | F27: BUNTING , SPOTTY | G27: 3 | H27: 40685.494 | I27: 4.95 | J27: 12909 | K27: United Kingdom | L27: Online Retail.xlsx|Online Retail|000199126 | M27: 554084 | N27: 23298 | O27: 12909 | P27: BUNTING , SPOTTY | Q27: 3 | R27: 4.95 | S27: 40685.494 | T27: United Kingdom | U27: 2011-05 | V27: 49500 | W27: 148500 | X27: 14.85 | Y27: FALSE | Z27: FALSE | AA27: FALSE | AB27: TRUE | AC27: FALSE | AD27: FALSE | AE27: TRUE | AF27: 2 | AG27: TRUE | AH27: Merchandise | AI27: FALSE | AJ27: FALSE | AK27: FALSE | AL27: FALSE | AM27: FALSE | AN27: FALSE | AO27: FALSE | AP27: MerchandiseSale | AQ27: TRUE | AR27: TRUE | AS27: TRUE | AT27: Description-only duplicate candidate; Code with multiple descriptions | AU27: IsDescriptionVariantDuplicate
A28: Online Retail.xlsx | B28: Online Retail | C28: 199146 | D28: 554084 | E28: 23298 | F28: SPOTTY BUNTING | G28: 3 | H28: 40685.494 | I28: 4.95 | J28: 12909 | K28: United Kingdom | L28: Online Retail.xlsx|Online Retail|000199146 | M28: 554084 | N28: 23298 | O28: 12909 | P28: SPOTTY BUNTING | Q28: 3 | R28: 4.95 | S28: 40685.494 | T28: United Kingdom | U28: 2011-05 | V28: 49500 | W28: 148500 | X28: 14.85 | Y28: FALSE | Z28: FALSE | AA28: FALSE | AB28: FALSE | AC28: FALSE | AD28: FALSE | AE28: TRUE | AF28: 2 | AG28: TRUE | AH28: Merchandise | AI28: FALSE | AJ28: FALSE | AK28: FALSE | AL28: FALSE | AM28: FALSE | AN28: FALSE | AO28: FALSE | AP28: MerchandiseSale | AQ28: TRUE | AR28: TRUE | AS28: TRUE | AT28: Description-only duplicate candidate; Code with multiple descriptions | AU28: IsDescriptionVariantDuplicate
A29: Online Retail.xlsx | B29: Online Retail | C29: 452370 | D29: 575335 | E29: 23203 | F29: JUMBO BAG DOILEY PATTERNS | G29: 300 | H29: 40856.581 | I29: 1.79 | J29: 12931 | K29: United Kingdom | L29: Online Retail.xlsx|Online Retail|000452370 | M29: 575335 | N29: 23203 | O29: 12931 | P29: JUMBO BAG DOILEY PATTERNS | Q29: 300 | R29: 1.79 | S29: 40856.581 | T29: United Kingdom | U29: 2011-11 | V29: 17900 | W29: 5370000 | X29: 537 | Y29: FALSE | Z29: FALSE | AA29: FALSE | AB29: FALSE | AC29: FALSE | AD29: FALSE | AE29: TRUE | AF29: 4 | AG29: TRUE | AH29: Merchandise | AI29: FALSE | AJ29: FALSE | AK29: FALSE | AL29: FALSE | AM29: FALSE | AN29: FALSE | AO29: FALSE | AP29: MerchandiseSale | AQ29: TRUE | AR29: TRUE | AS29: TRUE | AT29: Description-only duplicate candidate; Code with multiple descriptions | AU29: IsDescriptionVariantDuplicate
A30: Online Retail.xlsx | B30: Online Retail | C30: 452373 | D30: 575335 | E30: 23203 | F30: JUMBO BAG VINTAGE DOILY | G30: 300 | H30: 40856.581 | I30: 1.79 | J30: 12931 | K30: United Kingdom | L30: Online Retail.xlsx|Online Retail|000452373 | M30: 575335 | N30: 23203 | O30: 12931 | P30: JUMBO BAG VINTAGE DOILY | Q30: 300 | R30: 1.79 | S30: 40856.581 | T30: United Kingdom | U30: 2011-11 | V30: 17900 | W30: 5370000 | X30: 537 | Y30: FALSE | Z30: FALSE | AA30: FALSE | AB30: TRUE | AC30: FALSE | AD30: FALSE | AE30: TRUE | AF30: 4 | AG30: TRUE | AH30: Merchandise | AI30: FALSE | AJ30: FALSE | AK30: FALSE | AL30: FALSE | AM30: FALSE | AN30: FALSE | AO30: FALSE | AP30: MerchandiseSale | AQ30: TRUE | AR30: TRUE | AS30: TRUE | AT30: Description-only duplicate candidate; Code with multiple descriptions | AU30: IsDescriptionVariantDuplicate
A31: Online Retail.xlsx | B31: Online Retail | C31: 2 | D31: 536365 | E31: 85123A | F31: WHITE HANGING HEART T-LIGHT HOLDER | G31: 6 | H31: 40513.351 | I31: 2.55 | J31: 17850 | K31: United Kingdom | L31: Online Retail.xlsx|Online Retail|000000002 | M31: 536365 | N31: 85123A | O31: 17850 | P31: WHITE HANGING HEART T-LIGHT HOLDER | Q31: 6 | R31: 2.55 | S31: 40513.351 | T31: United Kingdom | U31: 2010-12 | V31: 25500 | W31: 153000 | X31: 15.3 | Y31: FALSE | Z31: FALSE | AA31: FALSE | AB31: FALSE | AC31: FALSE | AD31: FALSE | AE31: FALSE | AF31: 4 | AG31: TRUE | AH31: Merchandise | AI31: FALSE | AJ31: FALSE | AK31: FALSE | AL31: FALSE | AM31: FALSE | AN31: FALSE | AO31: FALSE | AP31: MerchandiseSale | AQ31: TRUE | AR31: TRUE | AS31: TRUE | AT31: Code with multiple descriptions | AU31: HasMultipleDescriptions
A32: Online Retail.xlsx | B32: Online Retail | C32: 3 | D32: 536365 | E32: 71053 | F32: WHITE METAL LANTERN | G32: 6 | H32: 40513.351 | I32: 3.39 | J32: 17850 | K32: United Kingdom | L32: Online Retail.xlsx|Online Retail|000000003 | M32: 536365 | N32: 71053 | O32: 17850 | P32: WHITE METAL LANTERN | Q32: 6 | R32: 3.39 | S32: 40513.351 | T32: United Kingdom | U32: 2010-12 | V32: 33900 | W32: 203400 | X32: 20.34 | Y32: FALSE | Z32: FALSE | AA32: FALSE | AB32: FALSE | AC32: FALSE | AD32: FALSE | AE32: FALSE | AF32: 2 | AG32: TRUE | AH32: Merchandise | AI32: FALSE | AJ32: FALSE | AK32: FALSE | AL32: FALSE | AM32: FALSE | AN32: FALSE | AO32: FALSE | AP32: MerchandiseSale | AQ32: TRUE | AR32: TRUE | AS32: TRUE | AT32: Code with multiple descriptions | AU32: HasMultipleDescriptions
A33: Online Retail.xlsx | B33: Online Retail | C33: 4 | D33: 536365 | E33: 84406B | F33: CREAM CUPID HEARTS COAT HANGER | G33: 8 | H33: 40513.351 | I33: 2.75 | J33: 17850 | K33: United Kingdom | L33: Online Retail.xlsx|Online Retail|000000004 | M33: 536365 | N33: 84406B | O33: 17850 | P33: CREAM CUPID HEARTS COAT HANGER | Q33: 8 | R33: 2.75 | S33: 40513.351 | T33: United Kingdom | U33: 2010-12 | V33: 27500 | W33: 220000 | X33: 22 | Y33: FALSE | Z33: FALSE | AA33: FALSE | AB33: FALSE | AC33: FALSE | AD33: FALSE | AE33: FALSE | AF33: 3 | AG33: TRUE | AH33: Merchandise | AI33: FALSE | AJ33: FALSE | AK33: FALSE | AL33: FALSE | AM33: FALSE | AN33: FALSE | AO33: FALSE | AP33: MerchandiseSale | AQ33: TRUE | AR33: TRUE | AS33: TRUE | AT33: Code with multiple descriptions | AU33: HasMultipleDescriptions
A34: Online Retail.xlsx | B34: Online Retail | C34: 10 | D34: 536366 | E34: 22632 | F34: HAND WARMER RED POLKA DOT | G34: 6 | H34: 40513.353 | I34: 1.85 | J34: 17850 | K34: United Kingdom | L34: Online Retail.xlsx|Online Retail|000000010 | M34: 536366 | N34: 22632 | O34: 17850 | P34: HAND WARMER RED POLKA DOT | Q34: 6 | R34: 1.85 | S34: 40513.353 | T34: United Kingdom | U34: 2010-12 | V34: 18500 | W34: 111000 | X34: 11.1 | Y34: FALSE | Z34: FALSE | AA34: FALSE | AB34: FALSE | AC34: FALSE | AD34: FALSE | AE34: FALSE | AF34: 2 | AG34: TRUE | AH34: Merchandise | AI34: FALSE | AJ34: FALSE | AK34: FALSE | AL34: FALSE | AM34: FALSE | AN34: FALSE | AO34: FALSE | AP34: MerchandiseSale | AQ34: TRUE | AR34: TRUE | AS34: TRUE | AT34: Code with multiple descriptions | AU34: HasMultipleDescriptions
A35: Online Retail.xlsx | B35: Online Retail | C35: 11 | D35: 536367 | E35: 84879 | F35: ASSORTED COLOUR BIRD ORNAMENT | G35: 32 | H35: 40513.357 | I35: 1.69 | J35: 13047 | K35: United Kingdom | L35: Online Retail.xlsx|Online Retail|000000011 | M35: 536367 | N35: 84879 | O35: 13047 | P35: ASSORTED COLOUR BIRD ORNAMENT | Q35: 32 | R35: 1.69 | S35: 40513.357 | T35: United Kingdom | U35: 2010-12 | V35: 16900 | W35: 540800 | X35: 54.08 | Y35: FALSE | Z35: FALSE | AA35: FALSE | AB35: FALSE | AC35: FALSE | AD35: FALSE | AE35: FALSE | AF35: 2 | AG35: TRUE | AH35: Merchandise | AI35: FALSE | AJ35: FALSE | AK35: FALSE | AL35: FALSE | AM35: FALSE | AN35: FALSE | AO35: FALSE | AP35: MerchandiseSale | AQ35: TRUE | AR35: TRUE | AS35: TRUE | AT35: Code with multiple descriptions | AU35: HasMultipleDescriptions
A36: Online Retail.xlsx | B36: Online Retail | C36: 16 | D36: 536367 | E36: 84969 | F36: BOX OF 6 ASSORTED COLOUR TEASPOONS | G36: 6 | H36: 40513.357 | I36: 4.25 | J36: 13047 | K36: United Kingdom | L36: Online Retail.xlsx|Online Retail|000000016 | M36: 536367 | N36: 84969 | O36: 13047 | P36: BOX OF 6 ASSORTED COLOUR TEASPOONS | Q36: 6 | R36: 4.25 | S36: 40513.357 | T36: United Kingdom | U36: 2010-12 | V36: 42500 | W36: 255000 | X36: 25.5 | Y36: FALSE | Z36: FALSE | AA36: FALSE | AB36: FALSE | AC36: FALSE | AD36: FALSE | AE36: FALSE | AF36: 2 | AG36: TRUE | AH36: Merchandise | AI36: FALSE | AJ36: FALSE | AK36: FALSE | AL36: FALSE | AM36: FALSE | AN36: FALSE | AO36: FALSE | AP36: MerchandiseSale | AQ36: TRUE | AR36: TRUE | AS36: TRUE | AT36: Code with multiple descriptions | AU36: HasMultipleDescriptions
A37: Online Retail.xlsx | B37: Online Retail | C37: 42 | D37: 536370 | E37: 22900 | F37: SET 2 TEA TOWELS I LOVE LONDON | G37: 24 | H37: 40513.365 | I37: 2.95 | J37: 12583 | K37: France | L37: Online Retail.xlsx|Online Retail|000000042 | M37: 536370 | N37: 22900 | O37: 12583 | P37: SET 2 TEA TOWELS I LOVE LONDON | Q37: 24 | R37: 2.95 | S37: 40513.365 | T37: France | U37: 2010-12 | V37: 29500 | W37: 708000 | X37: 70.8 | Y37: FALSE | Z37: FALSE | AA37: FALSE | AB37: TRUE | AC37: FALSE | AD37: FALSE | AE37: FALSE | AF37: 2 | AG37: TRUE | AH37: Merchandise | AI37: FALSE | AJ37: FALSE | AK37: FALSE | AL37: FALSE | AM37: FALSE | AN37: FALSE | AO37: FALSE | AP37: MerchandiseSale | AQ37: TRUE | AR37: TRUE | AS37: TRUE | AT37: Code with multiple descriptions | AU37: HasMultipleDescriptions
A38: Online Retail.xlsx | B38: Online Retail | C38: 49 | D38: 536372 | E38: 22632 | F38: HAND WARMER RED POLKA DOT | G38: 6 | H38: 40513.376 | I38: 1.85 | J38: 17850 | K38: United Kingdom | L38: Online Retail.xlsx|Online Retail|000000049 | M38: 536372 | N38: 22632 | O38: 17850 | P38: HAND WARMER RED POLKA DOT | Q38: 6 | R38: 1.85 | S38: 40513.376 | T38: United Kingdom | U38: 2010-12 | V38: 18500 | W38: 111000 | X38: 11.1 | Y38: FALSE | Z38: FALSE | AA38: FALSE | AB38: FALSE | AC38: FALSE | AD38: FALSE | AE38: FALSE | AF38: 2 | AG38: TRUE | AH38: Merchandise | AI38: FALSE | AJ38: FALSE | AK38: FALSE | AL38: FALSE | AM38: FALSE | AN38: FALSE | AO38: FALSE | AP38: MerchandiseSale | AQ38: TRUE | AR38: TRUE | AS38: TRUE | AT38: Code with multiple descriptions | AU38: HasMultipleDescriptions
A39: Online Retail.xlsx | B39: Online Retail | C39: 2408 | D39: 536589 | E39: 21777 | G39: -10 | H39: 40513.701 | I39: 0 | K39: United Kingdom | L39: Online Retail.xlsx|Online Retail|000002408 | M39: 536589 | N39: 21777 | Q39: -10 | R39: 0 | S39: 40513.701 | T39: United Kingdom | U39: 2010-12 | V39: 0 | W39: 0 | X39: 0 | Y39: TRUE | Z39: TRUE | AA39: FALSE | AB39: FALSE | AC39: FALSE | AD39: FALSE | AE39: FALSE | AF39: 1 | AG39: FALSE | AH39: Merchandise | AI39: FALSE | AJ39: FALSE | AK39: FALSE | AL39: TRUE | AM39: TRUE | AN39: FALSE | AO39: FALSE | AP39: ZeroPriceAdjustment | AQ39: FALSE | AR39: FALSE | AS39: TRUE | AT39: Missing customer ID; Missing description; Negative quantity without C; Zero price | AU39: IsNonCNegative
A40: Online Retail.xlsx | B40: Online Retail | C40: 4349 | D40: 536764 | E40: 84952C | G40: -38 | H40: 40514.613 | I40: 0 | K40: United Kingdom | L40: Online Retail.xlsx|Online Retail|000004349 | M40: 536764 | N40: 84952C | Q40: -38 | R40: 0 | S40: 40514.613 | T40: United Kingdom | U40: 2010-12 | V40: 0 | W40: 0 | X40: 0 | Y40: TRUE | Z40: TRUE | AA40: FALSE | AB40: FALSE | AC40: FALSE | AD40: FALSE | AE40: FALSE | AF40: 1 | AG40: FALSE | AH40: Merchandise | AI40: FALSE | AJ40: FALSE | AK40: FALSE | AL40: TRUE | AM40: TRUE | AN40: FALSE | AO40: FALSE | AP40: ZeroPriceAdjustment | AQ40: FALSE | AR40: FALSE | AS40: TRUE | AT40: Missing customer ID; Missing description; Negative quantity without C; Zero price | AU40: IsNonCNegative
A41: Online Retail.xlsx | B41: Online Retail | C41: 7190 | D41: 536996 | E41: 22712 | G41: -20 | H41: 40515.646 | I41: 0 | K41: United Kingdom | L41: Online Retail.xlsx|Online Retail|000007190 | M41: 536996 | N41: 22712 | Q41: -20 | R41: 0 | S41: 40515.646 | T41: United Kingdom | U41: 2010-12 | V41: 0 | W41: 0 | X41: 0 | Y41: TRUE | Z41: TRUE | AA41: FALSE | AB41: FALSE | AC41: FALSE | AD41: FALSE | AE41: FALSE | AF41: 1 | AG41: FALSE | AH41: Merchandise | AI41: FALSE | AJ41: FALSE | AK41: FALSE | AL41: TRUE | AM41: TRUE | AN41: FALSE | AO41: FALSE | AP41: ZeroPriceAdjustment | AQ41: FALSE | AR41: FALSE | AS41: TRUE | AT41: Missing customer ID; Missing description; Negative quantity without C; Zero price | AU41: IsNonCNegative
A42: Online Retail.xlsx | B42: Online Retail | C42: 7191 | D42: 536997 | E42: 22028 | G42: -20 | H42: 40515.646 | I42: 0 | K42: United Kingdom | L42: Online Retail.xlsx|Online Retail|000007191 | M42: 536997 | N42: 22028 | Q42: -20 | R42: 0 | S42: 40515.646 | T42: United Kingdom | U42: 2010-12 | V42: 0 | W42: 0 | X42: 0 | Y42: TRUE | Z42: TRUE | AA42: FALSE | AB42: FALSE | AC42: FALSE | AD42: FALSE | AE42: FALSE | AF42: 1 | AG42: FALSE | AH42: Merchandise | AI42: FALSE | AJ42: FALSE | AK42: FALSE | AL42: TRUE | AM42: TRUE | AN42: FALSE | AO42: FALSE | AP42: ZeroPriceAdjustment | AQ42: FALSE | AR42: FALSE | AS42: TRUE | AT42: Missing customer ID; Missing description; Negative quantity without C; Zero price | AU42: IsNonCNegative
A43: Online Retail.xlsx | B43: Online Retail | C43: 7192 | D43: 536998 | E43: 85067 | G43: -6 | H43: 40515.646 | I43: 0 | K43: United Kingdom | L43: Online Retail.xlsx|Online Retail|000007192 | M43: 536998 | N43: 85067 | Q43: -6 | R43: 0 | S43: 40515.646 | T43: United Kingdom | U43: 2010-12 | V43: 0 | W43: 0 | X43: 0 | Y43: TRUE | Z43: TRUE | AA43: FALSE | AB43: FALSE | AC43: FALSE | AD43: FALSE | AE43: FALSE | AF43: 1 | AG43: FALSE | AH43: Merchandise | AI43: FALSE | AJ43: FALSE | AK43: FALSE | AL43: TRUE | AM43: TRUE | AN43: FALSE | AO43: FALSE | AP43: ZeroPriceAdjustment | AQ43: FALSE | AR43: FALSE | AS43: TRUE | AT43: Missing customer ID; Missing description; Negative quantity without C; Zero price | AU43: IsNonCNegative
A44: Online Retail.xlsx | B44: Online Retail | C44: 7194 | D44: 537000 | E44: 21414 | G44: -22 | H44: 40515.647 | I44: 0 | K44: United Kingdom | L44: Online Retail.xlsx|Online Retail|000007194 | M44: 537000 | N44: 21414 | Q44: -22 | R44: 0 | S44: 40515.647 | T44: United Kingdom | U44: 2010-12 | V44: 0 | W44: 0 | X44: 0 | Y44: TRUE | Z44: TRUE | AA44: FALSE | AB44: FALSE | AC44: FALSE | AD44: FALSE | AE44: FALSE | AF44: 1 | AG44: FALSE | AH44: Merchandise | AI44: FALSE | AJ44: FALSE | AK44: FALSE | AL44: TRUE | AM44: TRUE | AN44: FALSE | AO44: FALSE | AP44: ZeroPriceAdjustment | AQ44: FALSE | AR44: FALSE | AS44: TRUE | AT44: Missing customer ID; Missing description; Negative quantity without C; Zero price | AU44: IsNonCNegative
A45: Online Retail.xlsx | B45: Online Retail | C45: 7195 | D45: 537001 | E45: 21653 | G45: -6 | H45: 40515.648 | I45: 0 | K45: United Kingdom | L45: Online Retail.xlsx|Online Retail|000007195 | M45: 537001 | N45: 21653 | Q45: -6 | R45: 0 | S45: 40515.648 | T45: United Kingdom | U45: 2010-12 | V45: 0 | W45: 0 | X45: 0 | Y45: TRUE | Z45: TRUE | AA45: FALSE | AB45: FALSE | AC45: FALSE | AD45: FALSE | AE45: FALSE | AF45: 0 | AG45: FALSE | AH45: Merchandise | AI45: FALSE | AJ45: FALSE | AK45: FALSE | AL45: TRUE | AM45: TRUE | AN45: FALSE | AO45: FALSE | AP45: ZeroPriceAdjustment | AQ45: FALSE | AR45: FALSE | AS45: TRUE | AT45: Missing customer ID; Missing description; Negative quantity without C; Zero price | AU45: IsNonCNegative
A46: Online Retail.xlsx | B46: Online Retail | C46: 7197 | D46: 537003 | E46: 85126 | G46: -2 | H46: 40515.648 | I46: 0 | K46: United Kingdom | L46: Online Retail.xlsx|Online Retail|000007197 | M46: 537003 | N46: 85126 | Q46: -2 | R46: 0 | S46: 40515.648 | T46: United Kingdom | U46: 2010-12 | V46: 0 | W46: 0 | X46: 0 | Y46: TRUE | Z46: TRUE | AA46: FALSE | AB46: FALSE | AC46: FALSE | AD46: FALSE | AE46: FALSE | AF46: 1 | AG46: FALSE | AH46: Merchandise | AI46: FALSE | AJ46: FALSE | AK46: FALSE | AL46: TRUE | AM46: TRUE | AN46: FALSE | AO46: FALSE | AP46: ZeroPriceAdjustment | AQ46: FALSE | AR46: FALSE | AS46: TRUE | AT46: Missing customer ID; Missing description; Negative quantity without C; Zero price | AU46: IsNonCNegative
A47: Online Retail.xlsx | B47: Online Retail | C47: 624 | D47: 536414 | E47: 22139 | G47: 56 | H47: 40513.494 | I47: 0 | K47: United Kingdom | L47: Online Retail.xlsx|Online Retail|000000624 | M47: 536414 | N47: 22139 | Q47: 56 | R47: 0 | S47: 40513.494 | T47: United Kingdom | U47: 2010-12 | V47: 0 | W47: 0 | X47: 0 | Y47: TRUE | Z47: TRUE | AA47: FALSE | AB47: FALSE | AC47: FALSE | AD47: FALSE | AE47: FALSE | AF47: 2 | AG47: TRUE | AH47: Merchandise | AI47: FALSE | AJ47: FALSE | AK47: FALSE | AL47: FALSE | AM47: TRUE | AN47: FALSE | AO47: FALSE | AP47: UnresolvedReview | AQ47: FALSE | AR47: FALSE | AS47: TRUE | AT47: Missing customer ID; Missing description; Code with multiple descriptions; Zero price; Unresolved transaction class | AU47: IsZeroPrice
A48: Online Retail.xlsx | B48: Online Retail | C48: 1972 | D48: 536545 | E48: 21134 | G48: 1 | H48: 40513.606 | I48: 0 | K48: United Kingdom | L48: Online Retail.xlsx|Online Retail|000001972 | M48: 536545 | N48: 21134 | Q48: 1 | R48: 0 | S48: 40513.606 | T48: United Kingdom | U48: 2010-12 | V48: 0 | W48: 0 | X48: 0 | Y48: TRUE | Z48: TRUE | AA48: FALSE | AB48: FALSE | AC48: FALSE | AD48: FALSE | AE48: FALSE | AF48: 0 | AG48: FALSE | AH48: Merchandise | AI48: FALSE | AJ48: FALSE | AK48: FALSE | AL48: FALSE | AM48: TRUE | AN48: FALSE | AO48: FALSE | AP48: UnresolvedReview | AQ48: FALSE | AR48: FALSE | AS48: TRUE | AT48: Missing customer ID; Missing description; Zero price; Unresolved transaction class | AU48: IsZeroPrice
A49: Online Retail.xlsx | B49: Online Retail | C49: 1973 | D49: 536546 | E49: 22145 | G49: 1 | H49: 40513.606 | I49: 0 | K49: United Kingdom | L49: Online Retail.xlsx|Online Retail|000001973 | M49: 536546 | N49: 22145 | Q49: 1 | R49: 0 | S49: 40513.606 | T49: United Kingdom | U49: 2010-12 | V49: 0 | W49: 0 | X49: 0 | Y49: TRUE | Z49: TRUE | AA49: FALSE | AB49: FALSE | AC49: FALSE | AD49: FALSE | AE49: FALSE | AF49: 1 | AG49: FALSE | AH49: Merchandise | AI49: FALSE | AJ49: FALSE | AK49: FALSE | AL49: FALSE | AM49: TRUE | AN49: FALSE | AO49: FALSE | AP49: UnresolvedReview | AQ49: FALSE | AR49: FALSE | AS49: TRUE | AT49: Missing customer ID; Missing description; Zero price; Unresolved transaction class | AU49: IsZeroPrice
A50: Online Retail.xlsx | B50: Online Retail | C50: 1974 | D50: 536547 | E50: 37509 | G50: 1 | H50: 40513.606 | I50: 0 | K50: United Kingdom | L50: Online Retail.xlsx|Online Retail|000001974 | M50: 536547 | N50: 37509 | Q50: 1 | R50: 0 | S50: 40513.606 | T50: United Kingdom | U50: 2010-12 | V50: 0 | W50: 0 | X50: 0 | Y50: TRUE | Z50: TRUE | AA50: FALSE | AB50: FALSE | AC50: FALSE | AD50: FALSE | AE50: FALSE | AF50: 1 | AG50: FALSE | AH50: Merchandise | AI50: FALSE | AJ50: FALSE | AK50: FALSE | AL50: FALSE | AM50: TRUE | AN50: FALSE | AO50: FALSE | AP50: UnresolvedReview | AQ50: FALSE | AR50: FALSE | AS50: TRUE | AT50: Missing customer ID; Missing description; Zero price; Unresolved transaction class | AU50: IsZeroPrice
A51: Online Retail.xlsx | B51: Online Retail | C51: 1989 | D51: 536549 | E51: 85226A | G51: 1 | H51: 40513.607 | I51: 0 | K51: United Kingdom | L51: Online Retail.xlsx|Online Retail|000001989 | M51: 536549 | N51: 85226A | Q51: 1 | R51: 0 | S51: 40513.607 | T51: United Kingdom | U51: 2010-12 | V51: 0 | W51: 0 | X51: 0 | Y51: TRUE | Z51: TRUE | AA51: FALSE | AB51: FALSE | AC51: FALSE | AD51: FALSE | AE51: FALSE | AF51: 0 | AG51: FALSE | AH51: Merchandise | AI51: FALSE | AJ51: FALSE | AK51: FALSE | AL51: FALSE | AM51: TRUE | AN51: FALSE | AO51: FALSE | AP51: UnresolvedReview | AQ51: FALSE | AR51: FALSE | AS51: TRUE | AT51: Missing customer ID; Missing description; Zero price; Unresolved transaction class | AU51: IsZeroPrice
A52: Online Retail.xlsx | B52: Online Retail | C52: 1990 | D52: 536550 | E52: 85044 | G52: 1 | H52: 40513.607 | I52: 0 | K52: United Kingdom | L52: Online Retail.xlsx|Online Retail|000001990 | M52: 536550 | N52: 85044 | Q52: 1 | R52: 0 | S52: 40513.607 | T52: United Kingdom | U52: 2010-12 | V52: 0 | W52: 0 | X52: 0 | Y52: TRUE | Z52: TRUE | AA52: FALSE | AB52: FALSE | AC52: FALSE | AD52: FALSE | AE52: FALSE | AF52: 0 | AG52: FALSE | AH52: Merchandise | AI52: FALSE | AJ52: FALSE | AK52: FALSE | AL52: FALSE | AM52: TRUE | AN52: FALSE | AO52: FALSE | AP52: UnresolvedReview | AQ52: FALSE | AR52: FALSE | AS52: TRUE | AT52: Missing customer ID; Missing description; Zero price; Unresolved transaction class | AU52: IsZeroPrice
A53: Online Retail.xlsx | B53: Online Retail | C53: 2026 | D53: 536552 | E53: 20950 | G53: 1 | H53: 40513.607 | I53: 0 | K53: United Kingdom | L53: Online Retail.xlsx|Online Retail|000002026 | M53: 536552 | N53: 20950 | Q53: 1 | R53: 0 | S53: 40513.607 | T53: United Kingdom | U53: 2010-12 | V53: 0 | W53: 0 | X53: 0 | Y53: TRUE | Z53: TRUE | AA53: FALSE | AB53: FALSE | AC53: FALSE | AD53: FALSE | AE53: FALSE | AF53: 0 | AG53: FALSE | AH53: Merchandise | AI53: FALSE | AJ53: FALSE | AK53: FALSE | AL53: FALSE | AM53: TRUE | AN53: FALSE | AO53: FALSE | AP53: UnresolvedReview | AQ53: FALSE | AR53: FALSE | AS53: TRUE | AT53: Missing customer ID; Missing description; Zero price; Unresolved transaction class | AU53: IsZeroPrice
A54: Online Retail.xlsx | B54: Online Retail | C54: 2027 | D54: 536553 | E54: 37461 | G54: 3 | H54: 40513.608 | I54: 0 | K54: United Kingdom | L54: Online Retail.xlsx|Online Retail|000002027 | M54: 536553 | N54: 37461 | Q54: 3 | R54: 0 | S54: 40513.608 | T54: United Kingdom | U54: 2010-12 | V54: 0 | W54: 0 | X54: 0 | Y54: TRUE | Z54: TRUE | AA54: FALSE | AB54: FALSE | AC54: FALSE | AD54: FALSE | AE54: FALSE | AF54: 1 | AG54: FALSE | AH54: Merchandise | AI54: FALSE | AJ54: FALSE | AK54: FALSE | AL54: FALSE | AM54: TRUE | AN54: FALSE | AO54: FALSE | AP54: UnresolvedReview | AQ54: FALSE | AR54: FALSE | AS54: TRUE | AT54: Missing customer ID; Missing description; Zero price; Unresolved transaction class | AU54: IsZeroPrice
A55: Online Retail.xlsx | B55: Online Retail | C55: 299985 | D55: A563186 | E55: B | F55: Adjust bad debt | G55: 1 | H55: 40767.619 | I55: -11062.06 | K55: United Kingdom | L55: Online Retail.xlsx|Online Retail|000299985 | M55: A563186 | N55: B | P55: Adjust bad debt | Q55: 1 | R55: -11062.06 | S55: 40767.619 | T55: United Kingdom | U55: 2011-08 | V55: -110620600 | W55: -110620600 | X55: -11062.06 | Y55: TRUE | Z55: FALSE | AA55: FALSE | AB55: FALSE | AC55: FALSE | AD55: FALSE | AE55: FALSE | AF55: 1 | AG55: FALSE | AH55: AccountingAdjustment | AI55: FALSE | AJ55: FALSE | AK55: TRUE | AL55: FALSE | AM55: FALSE | AN55: TRUE | AO55: TRUE | AP55: SpecialOperation | AQ55: FALSE | AR55: FALSE | AS55: TRUE | AT55: Missing customer ID; Negative price; Large absolute line amount | AU55: IsNegativePrice
A56: Online Retail.xlsx | B56: Online Retail | C56: 299986 | D56: A563187 | E56: B | F56: Adjust bad debt | G56: 1 | H56: 40767.619 | I56: -11062.06 | K56: United Kingdom | L56: Online Retail.xlsx|Online Retail|000299986 | M56: A563187 | N56: B | P56: Adjust bad debt | Q56: 1 | R56: -11062.06 | S56: 40767.619 | T56: United Kingdom | U56: 2011-08 | V56: -110620600 | W56: -110620600 | X56: -11062.06 | Y56: TRUE | Z56: FALSE | AA56: FALSE | AB56: FALSE | AC56: FALSE | AD56: FALSE | AE56: FALSE | AF56: 1 | AG56: FALSE | AH56: AccountingAdjustment | AI56: FALSE | AJ56: FALSE | AK56: TRUE | AL56: FALSE | AM56: FALSE | AN56: TRUE | AO56: TRUE | AP56: SpecialOperation | AQ56: FALSE | AR56: FALSE | AS56: TRUE | AT56: Missing customer ID; Negative price; Large absolute line amount | AU56: IsNegativePrice
A57: Online Retail.xlsx | B57: Online Retail | C57: 15018 | D57: C537630 | E57: AMAZONFEE | F57: AMAZON FEE | G57: -1 | H57: 40519.628 | I57: 13541.33 | K57: United Kingdom | L57: Online Retail.xlsx|Online Retail|000015018 | M57: C537630 | N57: AMAZONFEE | P57: AMAZON FEE | Q57: -1 | R57: 13541.33 | S57: 40519.628 | T57: United Kingdom | U57: 2010-12 | V57: 135413300 | W57: -135413300 | X57: -13541.33 | Y57: TRUE | Z57: FALSE | AA57: FALSE | AB57: FALSE | AC57: FALSE | AD57: FALSE | AE57: FALSE | AF57: 1 | AG57: FALSE | AH57: PlatformFee | AI57: FALSE | AJ57: TRUE | AK57: FALSE | AL57: FALSE | AM57: FALSE | AN57: FALSE | AO57: TRUE | AP57: SpecialOperation | AQ57: FALSE | AR57: FALSE | AS57: TRUE | AT57: Missing customer ID; Large absolute line amount | AU57: IsLargeAmount
A58: Online Retail.xlsx | B58: Online Retail | C58: 15019 | D58: 537632 | E58: AMAZONFEE | F58: AMAZON FEE | G58: 1 | H58: 40519.631 | I58: 13541.33 | K58: United Kingdom | L58: Online Retail.xlsx|Online Retail|000015019 | M58: 537632 | N58: AMAZONFEE | P58: AMAZON FEE | Q58: 1 | R58: 13541.33 | S58: 40519.631 | T58: United Kingdom | U58: 2010-12 | V58: 135413300 | W58: 135413300 | X58: 13541.33 | Y58: TRUE | Z58: FALSE | AA58: FALSE | AB58: FALSE | AC58: FALSE | AD58: FALSE | AE58: FALSE | AF58: 1 | AG58: FALSE | AH58: PlatformFee | AI58: FALSE | AJ58: FALSE | AK58: FALSE | AL58: FALSE | AM58: FALSE | AN58: FALSE | AO58: TRUE | AP58: SpecialOperation | AQ58: FALSE | AR58: FALSE | AS58: TRUE | AT58: Missing customer ID; Large absolute line amount | AU58: IsLargeAmount
A59: Online Retail.xlsx | B59: Online Retail | C59: 16234 | D59: C537644 | E59: AMAZONFEE | F59: AMAZON FEE | G59: -1 | H59: 40519.649 | I59: 13474.79 | K59: United Kingdom | L59: Online Retail.xlsx|Online Retail|000016234 | M59: C537644 | N59: AMAZONFEE | P59: AMAZON FEE | Q59: -1 | R59: 13474.79 | S59: 40519.649 | T59: United Kingdom | U59: 2010-12 | V59: 134747900 | W59: -134747900 | X59: -13474.79 | Y59: TRUE | Z59: FALSE | AA59: FALSE | AB59: FALSE | AC59: FALSE | AD59: FALSE | AE59: FALSE | AF59: 1 | AG59: FALSE | AH59: PlatformFee | AI59: FALSE | AJ59: TRUE | AK59: FALSE | AL59: FALSE | AM59: FALSE | AN59: FALSE | AO59: TRUE | AP59: SpecialOperation | AQ59: FALSE | AR59: FALSE | AS59: TRUE | AT59: Missing customer ID; Large absolute line amount | AU59: IsLargeAmount
A60: Online Retail.xlsx | B60: Online Retail | C60: 16358 | D60: C537651 | E60: AMAZONFEE | F60: AMAZON FEE | G60: -1 | H60: 40519.659 | I60: 13541.33 | K60: United Kingdom | L60: Online Retail.xlsx|Online Retail|000016358 | M60: C537651 | N60: AMAZONFEE | P60: AMAZON FEE | Q60: -1 | R60: 13541.33 | S60: 40519.659 | T60: United Kingdom | U60: 2010-12 | V60: 135413300 | W60: -135413300 | X60: -13541.33 | Y60: TRUE | Z60: FALSE | AA60: FALSE | AB60: FALSE | AC60: FALSE | AD60: FALSE | AE60: FALSE | AF60: 1 | AG60: FALSE | AH60: PlatformFee | AI60: FALSE | AJ60: TRUE | AK60: FALSE | AL60: FALSE | AM60: FALSE | AN60: FALSE | AO60: TRUE | AP60: SpecialOperation | AQ60: FALSE | AR60: FALSE | AS60: TRUE | AT60: Missing customer ID; Large absolute line amount | AU60: IsLargeAmount
A61: Online Retail.xlsx | B61: Online Retail | C61: 43704 | D61: C540117 | E61: AMAZONFEE | F61: AMAZON FEE | G61: -1 | H61: 40548.413 | I61: 16888.02 | K61: United Kingdom | L61: Online Retail.xlsx|Online Retail|000043704 | M61: C540117 | N61: AMAZONFEE | P61: AMAZON FEE | Q61: -1 | R61: 16888.02 | S61: 40548.413 | T61: United Kingdom | U61: 2011-01 | V61: 168880200 | W61: -168880200 | X61: -16888.02 | Y61: TRUE | Z61: FALSE | AA61: FALSE | AB61: FALSE | AC61: FALSE | AD61: FALSE | AE61: FALSE | AF61: 1 | AG61: FALSE | AH61: PlatformFee | AI61: FALSE | AJ61: TRUE | AK61: FALSE | AL61: FALSE | AM61: FALSE | AN61: FALSE | AO61: TRUE | AP61: SpecialOperation | AQ61: FALSE | AR61: FALSE | AS61: TRUE | AT61: Missing customer ID; Large absolute line amount | AU61: IsLargeAmount
A62: Online Retail.xlsx | B62: Online Retail | C62: 43705 | D62: C540118 | E62: AMAZONFEE | F62: AMAZON FEE | G62: -1 | H62: 40548.415 | I62: 16453.71 | K62: United Kingdom | L62: Online Retail.xlsx|Online Retail|000043705 | M62: C540118 | N62: AMAZONFEE | P62: AMAZON FEE | Q62: -1 | R62: 16453.71 | S62: 40548.415 | T62: United Kingdom | U62: 2011-01 | V62: 164537100 | W62: -164537100 | X62: -16453.71 | Y62: TRUE | Z62: FALSE | AA62: FALSE | AB62: FALSE | AC62: FALSE | AD62: FALSE | AE62: FALSE | AF62: 1 | AG62: FALSE | AH62: PlatformFee | AI62: FALSE | AJ62: TRUE | AK62: FALSE | AL62: FALSE | AM62: FALSE | AN62: FALSE | AO62: TRUE | AP62: SpecialOperation | AQ62: FALSE | AR62: FALSE | AS62: TRUE | AT62: Missing customer ID; Large absolute line amount | AU62: IsLargeAmount
A63: Online Retail.xlsx | B63: Online Retail | C63: 61621 | D63: 541431 | E63: 23166 | F63: MEDIUM CERAMIC TOP STORAGE JAR | G63: 74215 | H63: 40561.417 | I63: 1.04 | J63: 12346 | K63: United Kingdom | L63: Online Retail.xlsx|Online Retail|000061621 | M63: 541431 | N63: 23166 | O63: 12346 | P63: MEDIUM CERAMIC TOP STORAGE JAR | Q63: 74215 | R63: 1.04 | S63: 40561.417 | T63: United Kingdom | U63: 2011-01 | V63: 10400 | W63: 771836000 | X63: 77183.6 | Y63: FALSE | Z63: FALSE | AA63: FALSE | AB63: FALSE | AC63: FALSE | AD63: FALSE | AE63: FALSE | AF63: 1 | AG63: FALSE | AH63: Merchandise | AI63: FALSE | AJ63: FALSE | AK63: FALSE | AL63: FALSE | AM63: FALSE | AN63: FALSE | AO63: TRUE | AP63: MerchandiseSale | AQ63: TRUE | AR63: TRUE | AS63: TRUE | AT63: Large absolute line amount | AU63: IsLargeAmount
A64: Online Retail.xlsx | B64: Online Retail | C64: 61626 | D64: C541433 | E64: 23166 | F64: MEDIUM CERAMIC TOP STORAGE JAR | G64: -74215 | H64: 40561.428 | I64: 1.04 | J64: 12346 | K64: United Kingdom | L64: Online Retail.xlsx|Online Retail|000061626 | M64: C541433 | N64: 23166 | O64: 12346 | P64: MEDIUM CERAMIC TOP STORAGE JAR | Q64: -74215 | R64: 1.04 | S64: 40561.428 | T64: United Kingdom | U64: 2011-01 | V64: 10400 | W64: -771836000 | X64: -77183.6 | Y64: FALSE | Z64: FALSE | AA64: FALSE | AB64: FALSE | AC64: FALSE | AD64: FALSE | AE64: FALSE | AF64: 1 | AG64: FALSE | AH64: Merchandise | AI64: FALSE | AJ64: TRUE | AK64: FALSE | AL64: FALSE | AM64: FALSE | AN64: FALSE | AO64: TRUE | AP64: MerchandiseCancellation | AQ64: TRUE | AR64: FALSE | AS64: TRUE | AT64: Large absolute line amount | AU64: IsLargeAmount

Sheet DashboardData
A1: Country | B1: Month | C1: MonthDate | D1: SalesGBP | E1: CancellationGBP | F1: SalesRows | G1: KnownCustomerSalesRows | H1: SalesInvoiceIDs | I1: ReviewRows
A2: Australia | B2: 2010-12 | C2: 40513 | D2: 1032.85 | E2: 27.75 | F2: 32 | G2: 32 | H2: 3 | I2: 7
A3: Australia | B3: 2011-01 | C3: 40544 | D3: 9017.71 | E3: 0 | F3: 127 | G3: 127 | H3: 9 | I3: 25
A4: Australia | B4: 2011-02 | C4: 40575 | D4: 14695.42 | E4: 67.95 | F4: 89 | G4: 89 | H4: 5 | I4: 18
A5: Australia | B5: 2011-03 | C5: 40603 | D5: 17223.99 | E5: 168.7 | F5: 108 | G5: 108 | H5: 3 | I5: 15
A6: Australia | B6: 2011-04 | C6: 40634 | D6: 421.6 | E6: 438.2 | F6: 17 | G6: 17 | H6: 1 | I6: 5
A7: Australia | B7: 2011-05 | C7: 40664 | D7: 13638.41 | E7: 9.9 | F7: 116 | G7: 116 | H7: 4 | I7: 21
A8: Australia | B8: 2011-06 | C8: 40695 | D8: 25187.77 | E8: 23 | F8: 169 | G8: 169 | H8: 4 | I8: 36
A9: Australia | B9: 2011-07 | C9: 40725 | D9: 4964.38 | E9: 196.81 | F9: 159 | G9: 159 | H9: 7 | I9: 53
A10: Australia | B10: 2011-08 | C10: 40756 | D10: 22489.2 | E10: 0 | F10: 107 | G10: 107 | H10: 2 | I10: 28
A11: Australia | B11: 2011-09 | C11: 40787 | D11: 5106.73 | E11: 75 | F11: 102 | G11: 102 | H11: 8 | I11: 21
A12: Australia | B12: 2011-10 | C12: 40817 | D12: 17150.53 | E12: 0 | F12: 114 | G12: 114 | H12: 4 | I12: 31
A13: Australia | B13: 2011-11 | C13: 40848 | D13: 7242.72 | E13: 174 | F13: 41 | G13: 41 | H13: 6 | I13: 12
... A315: Unspecified | B315: 2011-11 | C315: 40848 | D315: 965.75 | E315: 0 | F315: 53 | G315: 0 | H315: 2 | I315: 53

Sheet RefreshInfo
A1: ExecutedAtUTC | B1: Mode
A2: 2026-10-12T08:33:17.842813+00:00 | B2: Reference dashboard | Embedded audit queries refreshed in Excel 2021; full-model integration pending

Sheet Lists
A1: All | B1: =IF(Monthly!A2="","",Monthly!A2) -> 2010-12
A2: =IF(Country!A2="","",Country!A2) -> United Kingdom | B2: =IF(Monthly!A3="","",Monthly!A3) -> 2011-01
A3: =IF(Country!A3="","",Country!A3) -> Netherlands | B3: =IF(Monthly!A4="","",Monthly!A4) -> 2011-02
A4: =IF(Country!A4="","",Country!A4) -> EIRE | B4: =IF(Monthly!A5="","",Monthly!A5) -> 2011-03
A5: =IF(Country!A5="","",Country!A5) -> Germany | B5: =IF(Monthly!A6="","",Monthly!A6) -> 2011-04
A6: =IF(Country!A6="","",Country!A6) -> France | B6: =IF(Monthly!A7="","",Monthly!A7) -> 2011-05
A7: =IF(Country!A7="","",Country!A7) -> Australia | B7: =IF(Monthly!A8="","",Monthly!A8) -> 2011-06
A8: =IF(Country!A8="","",Country!A8) -> Spain | B8: =IF(Monthly!A9="","",Monthly!A9) -> 2011-07
A9: =IF(Country!A9="","",Country!A9) -> Switzerland | B9: =IF(Monthly!A10="","",Monthly!A10) -> 2011-08
A10: =IF(Country!A10="","",Country!A10) -> Japan | B10: =IF(Monthly!A11="","",Monthly!A11) -> 2011-09
A11: =IF(Country!A11="","",Country!A11) -> Belgium | B11: =IF(Monthly!A12="","",Monthly!A12) -> 2011-10
A12: =IF(Country!A12="","",Country!A12) -> Sweden | B12: =IF(Monthly!A13="","",Monthly!A13) -> 2011-11
A13: =IF(Country!A13="","",Country!A13) -> Norway | B13: =IF(Monthly!A14="","",Monthly!A14) -> 2011-12
... A301: =IF(Country!A301="","",Country!A301) | B301: =IF(Monthly!A302="","",Monthly!A302)
B302: =IF(Monthly!A303="","",Monthly!A303)
B303: =IF(Monthly!A304="","",Monthly!A304)
B304: =IF(Monthly!A305="","",Monthly!A305)
B305: =IF(Monthly!A306="","",Monthly!A306)
B306: =IF(Monthly!A307="","",Monthly!A307)
B307: =IF(Monthly!A308="","",Monthly!A308)
B308: =IF(Monthly!A309="","",Monthly!A309)
B309: =IF(Monthly!A310="","",Monthly!A310)
B310: =IF(Monthly!A311="","",Monthly!A311)
B311: =IF(Monthly!A312="","",Monthly!A312)
B312: =IF(Monthly!A313="","",Monthly!A313)
B313: =IF(Monthly!A314="","",Monthly!A314)
... B1000: =IF(Monthly!A1001="","",Monthly!A1001)

Sheet ChartData
A1: Month | B1: Sales | C1: Cancellations (negative)
A2: =IF(Monthly!A2="","",Monthly!A2) -> 2010-12 | B2: =IF(AND(A2>=Dashboard!$F$5,A2<=Dashboard!$J$5,A2<>""),SUMIFS(DashboardData!$D:$D,DashboardData!$A:$A,IF(Dashboard!$B$5="All","*",Dashboard!$B$5),DashboardData!$B:$B,A2),NA()) -> 777931.77 | C2: =IF(AND(A2>=Dashboard!$F$5,A2<=Dashboard!$J$5,A2<>""),-SUMIFS(DashboardData!$E:$E,DashboardData!$A:$A,IF(Dashboard!$B$5="All","*",Dashboard!$B$5),DashboardData!$B:$B,A2),NA()) -> -17607.86
A3: =IF(Monthly!A3="","",Monthly!A3) -> 2011-01 | B3: =IF(AND(A3>=Dashboard!$F$5,A3<=Dashboard!$J$5,A3<>""),SUMIFS(DashboardData!$D:$D,DashboardData!$A:$A,IF(Dashboard!$B$5="All","*",Dashboard!$B$5),DashboardData!$B:$B,A3),NA()) -> 671933.19 | C3: =IF(AND(A3>=Dashboard!$F$5,A3<=Dashboard!$J$5,A3<>""),-SUMIFS(DashboardData!$E:$E,DashboardData!$A:$A,IF(Dashboard!$B$5="All","*",Dashboard!$B$5),DashboardData!$B:$B,A3),NA()) -> -91526.3
A4: =IF(Monthly!A4="","",Monthly!A4) -> 2011-02 | B4: =IF(AND(A4>=Dashboard!$F$5,A4<=Dashboard!$J$5,A4<>""),SUMIFS(DashboardData!$D:$D,DashboardData!$A:$A,IF(Dashboard!$B$5="All","*",Dashboard!$B$5),DashboardData!$B:$B,A4),NA()) -> 508886.2 | C4: =IF(AND(A4>=Dashboard!$F$5,A4<=Dashboard!$J$5,A4<>""),-SUMIFS(DashboardData!$E:$E,DashboardData!$A:$A,IF(Dashboard!$B$5="All","*",Dashboard!$B$5),DashboardData!$B:$B,A4),NA()) -> -8375.87
A5: =IF(Monthly!A5="","",Monthly!A5) -> 2011-03 | B5: =IF(AND(A5>=Dashboard!$F$5,A5<=Dashboard!$J$5,A5<>""),SUMIFS(DashboardData!$D:$D,DashboardData!$A:$A,IF(Dashboard!$B$5="All","*",Dashboard!$B$5),DashboardData!$B:$B,A5),NA()) -> 691257.61 | C5: =IF(AND(A5>=Dashboard!$F$5,A5<=Dashboard!$J$5,A5<>""),-SUMIFS(DashboardData!$E:$E,DashboardData!$A:$A,IF(Dashboard!$B$5="All","*",Dashboard!$B$5),DashboardData!$B:$B,A5),NA()) -> -10675.3
A6: =IF(Monthly!A6="","",Monthly!A6) -> 2011-04 | B6: =IF(AND(A6>=Dashboard!$F$5,A6<=Dashboard!$J$5,A6<>""),SUMIFS(DashboardData!$D:$D,DashboardData!$A:$A,IF(Dashboard!$B$5="All","*",Dashboard!$B$5),DashboardData!$B:$B,A6),NA()) -> 516218.12 | C6: =IF(AND(A6>=Dashboard!$F$5,A6<=Dashboard!$J$5,A6<>""),-SUMIFS(DashboardData!$E:$E,DashboardData!$A:$A,IF(Dashboard!$B$5="All","*",Dashboard!$B$5),DashboardData!$B:$B,A6),NA()) -> -33316.91
A7: =IF(Monthly!A7="","",Monthly!A7) -> 2011-05 | B7: =IF(AND(A7>=Dashboard!$F$5,A7<=Dashboard!$J$5,A7<>""),SUMIFS(DashboardData!$D:$D,DashboardData!$A:$A,IF(Dashboard!$B$5="All","*",Dashboard!$B$5),DashboardData!$B:$B,A7),NA()) -> 741192.41 | C7: =IF(AND(A7>=Dashboard!$F$5,A7<=Dashboard!$J$5,A7<>""),-SUMIFS(DashboardData!$E:$E,DashboardData!$A:$A,IF(Dashboard!$B$5="All","*",Dashboard!$B$5),DashboardData!$B:$B,A7),NA()) -> -8948.23
A8: =IF(Monthly!A8="","",Monthly!A8) -> 2011-06 | B8: =IF(AND(A8>=Dashboard!$F$5,A8<=Dashboard!$J$5,A8<>""),SUMIFS(DashboardData!$D:$D,DashboardData!$A:$A,IF(Dashboard!$B$5="All","*",Dashboard!$B$5),DashboardData!$B:$B,A8),NA()) -> 738751.87 | C8: =IF(AND(A8>=Dashboard!$F$5,A8<=Dashboard!$J$5,A8<>""),-SUMIFS(DashboardData!$E:$E,DashboardData!$A:$A,IF(Dashboard!$B$5="All","*",Dashboard!$B$5),DashboardData!$B:$B,A8),NA()) -> -13760.84
A9: =IF(Monthly!A9="","",Monthly!A9) -> 2011-07 | B9: =IF(AND(A9>=Dashboard!$F$5,A9<=Dashboard!$J$5,A9<>""),SUMIFS(DashboardData!$D:$D,DashboardData!$A:$A,IF(Dashboard!$B$5="All","*",Dashboard!$B$5),DashboardData!$B:$B,A9),NA()) -> 689364.41 | C9: =IF(AND(A9>=Dashboard!$F$5,A9<=Dashboard!$J$5,A9<>""),-SUMIFS(DashboardData!$E:$E,DashboardData!$A:$A,IF(Dashboard!$B$5="All","*",Dashboard!$B$5),DashboardData!$B:$B,A9),NA()) -> -11409.21
A10: =IF(Monthly!A10="","",Monthly!A10) -> 2011-08 | B10: =IF(AND(A10>=Dashboard!$F$5,A10<=Dashboard!$J$5,A10<>""),SUMIFS(DashboardData!$D:$D,DashboardData!$A:$A,IF(Dashboard!$B$5="All","*",Dashboard!$B$5),DashboardData!$B:$B,A10),NA()) -> 725513.5 | C10: =IF(AND(A10>=Dashboard!$F$5,A10<=Dashboard!$J$5,A10<>""),-SUMIFS(DashboardData!$E:$E,DashboardData!$A:$A,IF(Dashboard!$B$5="All","*",Dashboard!$B$5),DashboardData!$B:$B,A10),NA()) -> -22929.52
A11: =IF(Monthly!A11="","",Monthly!A11) -> 2011-09 | B11: =IF(AND(A11>=Dashboard!$F$5,A11<=Dashboard!$J$5,A11<>""),SUMIFS(DashboardData!$D:$D,DashboardData!$A:$A,IF(Dashboard!$B$5="All","*",Dashboard!$B$5),DashboardData!$B:$B,A11),NA()) -> 1030475.4 | C11: =IF(AND(A11>=Dashboard!$F$5,A11<=Dashboard!$J$5,A11<>""),-SUMIFS(DashboardData!$E:$E,DashboardData!$A:$A,IF(Dashboard!$B$5="All","*",Dashboard!$B$5),DashboardData!$B:$B,A11),NA()) -> -17044.68
A12: =IF(Monthly!A12="","",Monthly!A12) -> 2011-10 | B12: =IF(AND(A12>=Dashboard!$F$5,A12<=Dashboard!$J$5,A12<>""),SUMIFS(DashboardData!$D:$D,DashboardData!$A:$A,IF(Dashboard!$B$5="All","*",Dashboard!$B$5),DashboardData!$B:$B,A12),NA()) -> 1106669.8 | C12: =IF(AND(A12>=Dashboard!$F$5,A12<=Dashboard!$J$5,A12<>""),-SUMIFS(DashboardData!$E:$E,DashboardData!$A:$A,IF(Dashboard!$B$5="All","*",Dashboard!$B$5),DashboardData!$B:$B,A12),NA()) -> -43992.16
A13: =IF(Monthly!A13="","",Monthly!A13) -> 2011-11 | B13: =IF(AND(A13>=Dashboard!$F$5,A13<=Dashboard!$J$5,A13<>""),SUMIFS(DashboardData!$D:$D,DashboardData!$A:$A,IF(Dashboard!$B$5="All","*",Dashboard!$B$5),DashboardData!$B:$B,A13),NA()) -> 1457745.5 | C13: =IF(AND(A13>=Dashboard!$F$5,A13<=Dashboard!$J$5,A13<>""),-SUMIFS(DashboardData!$E:$E,DashboardData!$A:$A,IF(Dashboard!$B$5="All","*",Dashboard!$B$5),DashboardData!$B:$B,A13),NA()) -> -25010.54
... A1001: =IF(Monthly!A1001="","",Monthly!A1001) | B1001: =IF(AND(A1001>=Dashboard!$F$5,A1001<=Dashboard!$J$5,A1001<>""),SUMIFS(DashboardData!$D:$D,DashboardData!$A:$A,IF(Dashboard!$B$5="All","*",Dashboard!$B$5),DashboardData!$B:$B,A1001),NA()) -> #N/A | C1001: =IF(AND(A1001>=Dashboard!$F$5,A1001<=Dashboard!$J$5,A1001<>""),-SUMIFS(DashboardData!$E:$E,DashboardData!$A:$A,IF(Dashboard!$B$5="All","*",Dashboard!$B$5),DashboardData!$B:$B,A1001),NA()) -> #N/A
